Workbook
Name AIR: SYS!$C$13
Name ANR: SYS!$I$5:$Q$360
Name ARF: SYS!$I$2:$Q$2
Name BB: TRN!$A$2
Name BLT: TRN!$V$3
Name CO2Max: SYS!$C$9
Name CO2Tax: SYS!$C$8
Name COM: SYS!$H$4
Name D0: SYS!$C$5
Name DB: SYS!$C$6
Name DE: SYS!$C$7
Name DELTA: SYS!$C$12
Name FATX: SYS!$C$14
Name KTmax: TRN!$M$4:$M$464
Name KTmin: TRN!$L$4:$L$464
Name LFCF: SYS!$C$20
Name LOSS: TRN!$K$4:$K$464
Name MAX_SNSP: SYS!$I$3:$Q$3
Name MFLOW: TRN!$H$4:$I$464
Name NMD: SYS!$C$30:$C$41
Name NN: SYS!$G$4
Name O_M_rate: TRN!$U$3
Name QN: SYS!$C$18:$C$19
Name RS: SYS!$C$17
Name SCALE: SYS!$C$16
Name SNN: SYS!$C$18:$C$19
Name SOMAX: SYS!$C$11
Name SOMIN: SYS!$C$10
Name SVR: SYS!$C$15
Name T0: SYS!$C$4
Name TFC: TRN!$J$4:$J$464
Name TI: TRN!$D$4:$E$464
Name UCF: SYS!#REF!
Name XX: TRN!$G$4:$G$464

Sheet SYS
W1: 6 | X1: 47 | Y1: 73 | Z1: 99 | AA1: 176 | AB1: 207 | AC1: 226 | AD1: 227 | AE1: 273 | AF1: 279 | AG1: 325
H2: Area Selection | I2: 1 | J2: 1 | K2: 1 | L2: 1 | M2: 1 | N2: 1 | O2: 1 | P2: 1 | Q2: 1 | R2: (0:Ignored, 1:Normal, 2:Aggregated)
B3: System Settings | G3: Number of Nodes | H3: Number of Areas | I3: -1 | J3: -1 | K3: -1 | L3: -1 | M3: -1 | N3: -1 | O3: -1 | P3: -1 | Q3: -1 | R3: ←SNSP
B4: The Number of Time Steps per Day | C4: 24 | G4: =ROWS(ANR) -> 356 | H4: =COLUMNS(ANR) -> 9 | I4: Hokkaido | J4: Tohoku | K4: Kanto | L4: Chubu | M4: Hokuriku | N4: Kansai | O4: Shikoku | P4: Chugoku | Q4: Kyusyu | R4: CheckSum
B5: The Number of Days per Year | C5: =SUM(NMD) -> 365 | E5: 0 | F5: nab | G5: 0 | H5: 西当別変電所 | I5: 1 | J5: 0 | K5: 0 | L5: 0 | M5: 0 | N5: 0 | O5: 0 | P5: 0 | Q5: 0 | R5: =SUM(I5:Q5) -> 1 | S5: =SUM(R5:R360) -> 356
B6: The Beginning Day | C6: 91 | E6: 1 | F6: nno | G6: 1 | H6: 西野変電所 | I6: 1 | J6: 0 | K6: 0 | L6: 0 | M6: 0 | N6: 0 | O6: 0 | P6: 0 | Q6: 0 | R6: =SUM(I6:Q6) -> 1
B7: The Ending Day | C7: 272 | E7: 2 | F7: nfb | G7: 2 | H7: 西双葉開閉所 | I7: 1 | J7: 0 | K7: 0 | L7: 0 | M7: 0 | N7: 0 | O7: 0 | P7: 0 | Q7: 0 | R7: =SUM(I7:Q7) -> 1
B8: Carbon Tax [kYen/t-CO2] | C8: 0 | D8: 0 | E8: 3 | F8: msb | G8: 3 | H8: 南早来変電所 | I8: 1 | J8: 0 | K8: 0 | L8: 0 | M8: 0 | N8: 0 | O8: 0 | P8: 0 | Q8: 0 | R8: =SUM(I8:Q8) -> 1
B9: Carbon Limit [Mt-CO2/year] | C9: 0 | D9: 10 | E9: 4 | F9: neh | G9: 4 | H9: 苗穂変電所 | I9: 1 | J9: 0 | K9: 0 | L9: 0 | M9: 0 | N9: 0 | O9: 0 | P9: 0 | Q9: 0 | R9: =SUM(I9:Q9) -> 1
B10: Synthetic Oil Production Minimum Level [Mtoe/year] | C10: 0 | E10: 5 | F10: sno | G10: 5 | H10: 篠路変電所 | I10: 1 | J10: 0 | K10: 0 | L10: 0 | M10: 0 | N10: 0 | O10: 0 | P10: 0 | Q10: 0 | R10: =SUM(I10:Q10) -> 1 | AL10: =484*0.74 -> 358.16
B11: Synthetic Oil Production Maximum Level [Mtoe/year] | C11: -1 | E11: 6 | F11: nsp | G11: 6 | H11: 西札幌変電所 | I11: 1 | J11: 0 | K11: 0 | L11: 0 | M11: 0 | N11: 0 | O11: 0 | P11: 0 | Q11: 0 | R11: =SUM(I11:Q11) -> 1
B12: Capacity Reserve Ratio | C12: 0.08 | E12: 7 | F12: ftb | G12: 7 | H12: 双葉開閉所 | I12: 1 | J12: 0 | K12: 0 | L12: 0 | M12: 0 | N12: 0 | O12: 0 | P12: 0 | Q12: 0 | R12: =SUM(I12:Q12) -> 1
B13: Annual Interest Rate | C13: 0.03 | E13: 8 | F13: nmr | G13: 8 | H13: 西室蘭開閉所 | I13: 1 | J13: 0 | K13: 0 | L13: 0 | M13: 0 | N13: 0 | O13: 0 | P13: 0 | Q13: 0 | R13: =SUM(I13:Q13) -> 1
B14: Fixed Assets Tax Rate | C14: 0.014 | E14: 9 | F14: mrn | G14: 9 | H14: 室蘭変電所 | I14: 1 | J14: 0 | K14: 0 | L14: 0 | M14: 0 | N14: 0 | O14: 0 | P14: 0 | Q14: 0 | R14: =SUM(I14:Q14) -> 1
B15: Salvage Value Rate | C15: 0 | E15: 10 | F15: mkj | G15: 10 | H15: 南九条変電所 | I15: 1 | J15: 0 | K15: 0 | L15: 0 | M15: 0 | N15: 0 | O15: 0 | P15: 0 | Q15: 0 | R15: =SUM(I15:Q15) -> 1
B16: scale | C16: 1000 | E16: 11 | F16: not | G16: 11 | H16: 西小樽変電所 | I16: 1 | J16: 0 | K16: 0 | L16: 0 | M16: 0 | N16: 0 | O16: 0 | P16: 0 | Q16: 0 | R16: =SUM(I16:Q16) -> 1
B17: Time Slots Aggregation Number (Divisor of 24) | C17: 3 | E17: 12 | F17: tmk | G17: 12 | H17: 苫小牧変電所 | I17: 1 | J17: 0 | K17: 0 | L17: 0 | M17: 0 | N17: 0 | O17: 0 | P17: 0 | Q17: 0 | R17: =SUM(I17:Q17) -> 1
B18: Maximum No. of Cutting Planes | C18: 200 | E18: 13 | F18: tib | G18: 13 | H18: 追分開閉所 | I18: 1 | J18: 0 | K18: 0 | L18: 0 | M18: 0 | N18: 0 | O18: 0 | P18: 0 | Q18: 0 | R18: =SUM(I18:Q18) -> 1
B19: Maximum No. of Extreme Points of Convex Hull | C19: 200 | E19: 14 | F19: eni | G19: 14 | H19: 恵庭変電所 | I19: 1 | J19: 0 | K19: 0 | L19: 0 | M19: 0 | N19: 0 | O19: 0 | P19: 0 | Q19: 0 | R19: =SUM(I19:Q19) -> 1
B20: LFC Control Reserve Market Fee [Yen/kW] | C20: 0.01 | E20: 15 | F20: msp | G20: 15 | H20: 南札幌変電所 | I20: 1 | J20: 0 | K20: 0 | L20: 0 | M20: 0 | N20: 0 | O20: 0 | P20: 0 | Q20: 0 | R20: =SUM(I20:Q20) -> 1
E21: 16 | F21: keb | G21: 16 | H21: 北江別変電所 | I21: 1 | J21: 0 | K21: 0 | L21: 0 | M21: 0 | N21: 0 | O21: 0 | P21: 0 | Q21: 0 | R21: =SUM(I21:Q21) -> 1
E22: 17 | F22: hkt | G22: 17 | H22: 北斗変換所 | I22: 1 | J22: 0 | K22: 0 | L22: 0 | M22: 0 | N22: 0 | O22: 0 | P22: 0 | Q22: 0 | R22: =SUM(I22:Q22) -> 1
E23: 18 | F23: oon | G23: 18 | H23: 大野変電所 | I23: 1 | J23: 0 | K23: 0 | L23: 0 | M23: 0 | N23: 0 | O23: 0 | P23: 0 | Q23: 0 | R23: =SUM(I23:Q23) -> 1
E24: 19 | F24: nne | G24: 19 | H24: 北七飯変電所 | I24: 1 | J24: 0 | K24: 0 | L24: 0 | M24: 0 | N24: 0 | O24: 0 | P24: 0 | Q24: 0 | R24: =SUM(I24:Q24) -> 1
E25: 20 | F25: ary | G25: 20 | H25: 旭川嵐山開閉所 | I25: 1 | J25: 0 | K25: 0 | L25: 0 | M25: 0 | N25: 0 | O25: 0 | P25: 0 | Q25: 0 | R25: =SUM(I25:Q25) -> 1
E26: 21 | F26: akw | G26: 21 | H26: 旭川変電所 | I26: 1 | J26: 0 | K26: 0 | L26: 0 | M26: 0 | N26: 0 | O26: 0 | P26: 0 | Q26: 0 | R26: =SUM(I26:Q26) -> 1
E27: 22 | F27: nny | G27: 22 | H27: 西名寄変電所 | I27: 1 | J27: 0 | K27: 0 | L27: 0 | M27: 0 | N27: 0 | O27: 0 | P27: 0 | Q27: 0 | R27: =SUM(I27:Q27) -> 1
E28: 23 | F28: nas | G28: 23 | H28: 西旭川変電所 | I28: 1 | J28: 0 | K28: 0 | L28: 0 | M28: 0 | N28: 0 | O28: 0 | P28: 0 | Q28: 0 | R28: =SUM(I28:Q28) -> 1
E29: 24 | F29: ntw | G29: 24 | H29: 西滝川変電所 | I29: 1 | J29: 0 | K29: 0 | L29: 0 | M29: 0 | N29: 0 | O29: 0 | P29: 0 | Q29: 0 | R29: =SUM(I29:Q29) -> 1
B30: January | C30: 31 | D30: =D29+C30 -> 31 | E30: 25 | F30: kar | G30: 25 | H30: 北新得変電所 | I30: 1 | J30: 0 | K30: 0 | L30: 0 | M30: 0 | N30: 0 | O30: 0 | P30: 0 | Q30: 0 | R30: =SUM(I30:Q30) -> 1
B31: February | C31: 28 | D31: =D30+C31 -> 59 | E31: 26 | F31: isz | G31: 26 | H31: 岩清水開閉所 | I31: 1 | J31: 0 | K31: 0 | L31: 0 | M31: 0 | N31: 0 | O31: 0 | P31: 0 | Q31: 0 | R31: =SUM(I31:Q31) -> 1
B32: March | C32: 31 | D32: =D31+C32 -> 90 | E32: 27 | F32: kmm | G32: 27 | H32: 北芽室変電所 | I32: 1 | J32: 0 | K32: 0 | L32: 0 | M32: 0 | N32: 0 | O32: 0 | P32: 0 | Q32: 0 | R32: =SUM(I32:Q32) -> 1
B33: April | C33: 30 | D33: =D32+C33 -> 120 | E33: 28 | F33: nos | G33: 28 | H33: 西音更変電所 | I33: 1 | J33: 0 | K33: 0 | L33: 0 | M33: 0 | N33: 0 | O33: 0 | P33: 0 | Q33: 0 | R33: =SUM(I33:Q33) -> 1
B34: May | C34: 31 | D34: =D33+C34 -> 151 | E34: 29 | F34: umb | G34: 29 | H34: 宇円別変電所 | I34: 1 | J34: 0 | K34: 0 | L34: 0 | M34: 0 | N34: 0 | O34: 0 | P34: 0 | Q34: 0 | R34: =SUM(I34:Q34) -> 1
B35: June | C35: 30 | D35: =D34+C35 -> 181 | E35: 30 | F35: hkr | G35: 30 | H35: 東釧路変電所 | I35: 1 | J35: 0 | K35: 0 | L35: 0 | M35: 0 | N35: 0 | O35: 0 | P35: 0 | Q35: 0 | R35: =SUM(I35:Q35) -> 1
B36: July | C36: 31 | D36: =D35+C36 -> 212 | E36: 31 | F36: nhb | G36: 31 | H36: 西春別変電所 | I36: 1 | J36: 0 | K36: 0 | L36: 0 | M36: 0 | N36: 0 | O36: 0 | P36: 0 | Q36: 0 | R36: =SUM(I36:Q36) -> 1
B37: August | C37: 31 | D37: =D36+C37 -> 243 | E37: 32 | F37: hkd | G37: 32 | H37: 電発函館変換所 | I37: 1 | J37: 0 | K37: 0 | L37: 0 | M37: 0 | N37: 0 | O37: 0 | P37: 0 | Q37: 0 | R37: =SUM(I37:Q37) -> 1
B38: September | C38: 30 | D38: =D37+C38 -> 273 | E38: 33 | F38: uwk | G38: 33 | H38: 上北変電所 | I38: 0 | J38: 1 | K38: 0 | L38: 0 | M38: 0 | N38: 0 | O38: 0 | P38: 0 | Q38: 0 | R38: =SUM(I38:Q38) -> 1
B39: October | C39: 31 | D39: =D38+C39 -> 304 | E39: 34 | F39: iwt | G39: 34 | H39: 岩手変電所 | I39: 0 | J39: 1 | K39: 0 | L39: 0 | M39: 0 | N39: 0 | O39: 0 | P39: 0 | Q39: 0 | R39: =SUM(I39:Q39) -> 1
B40: November | C40: 30 | D40: =D39+C40 -> 334 | E40: 35 | F40: myg | G40: 35 | H40: 宮城変電所 | I40: 0 | J40: 1 | K40: 0 | L40: 0 | M40: 0 | N40: 0 | O40: 0 | P40: 0 | Q40: 0 | R40: =SUM(I40:Q40) -> 1
B41: December | C41: 31 | D41: =D40+C41 -> 365 | E41: 36 | F41: nsd | G41: 36 | H41: 西仙台変電所 | I41: 0 | J41: 1 | K41: 0 | L41: 0 | M41: 0 | N41: 0 | O41: 0 | P41: 0 | Q41: 0 | R41: =SUM(I41:Q41) -> 1
E42: 37 | F42: sma | G42: 37 | H42: 南相馬変電所 | I42: 0 | J42: 1 | K42: 0 | L42: 0 | M42: 0 | N42: 0 | O42: 0 | P42: 0 | Q42: 0 | R42: =SUM(I42:Q42) -> 1
E43: 38 | F43: aom | G43: 38 | H43: 青森変電所 | I43: 0 | J43: 1 | K43: 0 | L43: 0 | M43: 0 | N43: 0 | O43: 0 | P43: 0 | Q43: 0 | R43: =SUM(I43:Q43) -> 1
E44: 39 | F44: nsr | G44: 39 | H44: 能代変電所 | I44: 0 | J44: 1 | K44: 0 | L44: 0 | M44: 0 | N44: 0 | O44: 0 | P44: 0 | Q44: 0 | R44: =SUM(I44:Q44) -> 1
E45: 40 | F45: akt | G45: 40 | H45: 秋田変電所 | I45: 0 | J45: 1 | K45: 0 | L45: 0 | M45: 0 | N45: 0 | O45: 0 | P45: 0 | Q45: 0 | R45: =SUM(I45:Q45) -> 1
E46: 41 | F46: szk | G46: 41 | H46: 雫石開閉所 | I46: 0 | J46: 1 | K46: 0 | L46: 0 | M46: 0 | N46: 0 | O46: 0 | P46: 0 | Q46: 0 | R46: =SUM(I46:Q46) -> 1
E47: 42 | F47: ugo | G47: 42 | H47: 羽後変電所 | I47: 0 | J47: 1 | K47: 0 | L47: 0 | M47: 0 | N47: 0 | O47: 0 | P47: 0 | Q47: 0 | R47: =SUM(I47:Q47) -> 1
E48: 43 | F48: mzs | G48: 43 | H48: 水沢変電所 | I48: 0 | J48: 1 | K48: 0 | L48: 0 | M48: 0 | N48: 0 | O48: 0 | P48: 0 | Q48: 0 | R48: =SUM(I48:Q48) -> 1
E49: 44 | F49: snj | G49: 44 | H49: 新庄変電所 | I49: 0 | J49: 1 | K49: 0 | L49: 0 | M49: 0 | N49: 0 | O49: 0 | P49: 0 | Q49: 0 | R49: =SUM(I49:Q49) -> 1
E50: 45 | F50: nya | G50: 45 | H50: 西山形変電所 | I50: 0 | J50: 1 | K50: 0 | L50: 0 | M50: 0 | N50: 0 | O50: 0 | P50: 0 | Q50: 0 | R50: =SUM(I50:Q50) -> 1
E51: 46 | F51: ism | G51: 46 | H51: 石巻変電所 | I51: 0 | J51: 1 | K51: 0 | L51: 0 | M51: 0 | N51: 0 | O51: 0 | P51: 0 | Q51: 0 | R51: =SUM(I51:Q51) -> 1
E52: 47 | F52: sdi | G52: 47 | H52: 仙台変電所 | I52: 0 | J52: 1 | K52: 0 | L52: 0 | M52: 0 | N52: 0 | O52: 0 | P52: 0 | Q52: 0 | R52: =SUM(I52:Q52) -> 1
E53: 48 | F53: hsd | G53: 48 | H53: 東仙台変電所 | I53: 0 | J53: 1 | K53: 0 | L53: 0 | M53: 0 | N53: 0 | O53: 0 | P53: 0 | Q53: 0 | R53: =SUM(I53:Q53) -> 1
... E65: 62 | F65: ibt | G65: 60 | H65: 今別変換所 | I65: 0 | J65: 1 | K65: 0 | L65: 0 | M65: 0 | N65: 0 | O65: 0 | P65: 0 | Q65: 0 | R65: =SUM(I65:Q65) -> 1
F66: fkn | G66: 61 | H66: 旧福島第二原子力 | I66: 0 | J66: 0 | K66: 1 | L66: 0 | M66: 0 | N66: 0 | O66: 0 | P66: 0 | Q66: 0 | R66: =SUM(I66:Q66) -> 1
E67: 58 | F67: sfu | G67: 62 | H67: 新福島変電所 | I67: 0 | J67: 0 | K67: 1 | L67: 0 | M67: 0 | N67: 0 | O67: 0 | P67: 0 | Q67: 0 | R67: =SUM(I67:Q67) -> 1
E68: 61 | F68: miw | G68: 63 | H68: 南いわき開閉所 | I68: 0 | J68: 0 | K68: 1 | L68: 0 | M68: 0 | N68: 0 | O68: 0 | P68: 0 | Q68: 0 | R68: =SUM(I68:Q68) -> 1
E69: 63 | F69: siw | G69: 64 | H69: 新いわき開閉所 | I69: 0 | J69: 0 | K69: 1 | L69: 0 | M69: 0 | N69: 0 | O69: 0 | P69: 0 | Q69: 0 | R69: =SUM(I69:Q69) -> 1
E70: 64 | F70: hgm | G70: 65 | H70: 東群馬変電所 | I70: 0 | J70: 0 | K70: 1 | L70: 0 | M70: 0 | N70: 0 | O70: 0 | P70: 0 | Q70: 0 | R70: =SUM(I70:Q70) -> 1
E71: 65 | F71: sii | G71: 66 | H71: 新今市開閉所 | I71: 0 | J71: 0 | K71: 1 | L71: 0 | M71: 0 | N71: 0 | O71: 0 | P71: 0 | Q71: 0 | R71: =SUM(I71:Q71) -> 1
E72: 66 | F72: smg | G72: 67 | H72: 新茂木変電所 | I72: 0 | J72: 0 | K72: 1 | L72: 0 | M72: 0 | N72: 0 | O72: 0 | P72: 0 | Q72: 0 | R72: =SUM(I72:Q72) -> 1
E73: 67 | F73: stb | G73: 68 | H73: 新筑波変電所 | I73: 0 | J73: 0 | K73: 1 | L73: 0 | M73: 0 | N73: 0 | O73: 0 | P73: 0 | Q73: 0 | R73: =SUM(I73:Q73) -> 1
E74: 68 | F74: stg | G74: 69 | H74: 新栃木変電所 | I74: 0 | J74: 0 | K74: 1 | L74: 0 | M74: 0 | N74: 0 | O74: 0 | P74: 0 | Q74: 0 | R74: =SUM(I74:Q74) -> 1
E75: 69 | F75: nka | G75: 70 | H75: 那珂変電所 | I75: 0 | J75: 0 | K75: 1 | L75: 0 | M75: 0 | N75: 0 | O75: 0 | P75: 0 | Q75: 0 | R75: =SUM(I75:Q75) -> 1
E76: 70 | F76: sko | G76: 71 | H76: 新古河変電所 | I76: 0 | J76: 0 | K76: 1 | L76: 0 | M76: 0 | N76: 0 | O76: 0 | P76: 0 | Q76: 0 | R76: =SUM(I76:Q76) -> 1
E77: 71 | F77: sar | G77: 72 | H77: 新新田変電所 | I77: 0 | J77: 0 | K77: 1 | L77: 0 | M77: 0 | N77: 0 | O77: 0 | P77: 0 | Q77: 0 | R77: =SUM(I77:Q77) -> 1
E78: 72 | F78: ksz | G78: 73 | H78: 新木更津変電所 | I78: 0 | J78: 0 | K78: 1 | L78: 0 | M78: 0 | N78: 0 | O78: 0 | P78: 0 | Q78: 0 | R78: =SUM(I78:Q78) -> 1
... E86: 80 | F86: ssd | G86: 81 | H86: 新坂戸変電所 | I86: 0 | J86: 0 | K86: 1 | L86: 0 | M86: 0 | N86: 0 | O86: 0 | P86: 0 | Q86: 0 | R86: =SUM(I86:Q86) -> 1
F87: kzk | G87: 82 | H87: 柏崎刈羽原子力 | I87: 0 | J87: 0 | K87: 1 | L87: 0 | M87: 0 | N87: 0 | O87: 0 | P87: 0 | Q87: 0 | R87: =SUM(I87:Q87) -> 1
E88: 81 | F88: ngm | G88: 83 | H88: 西群馬開閉所 | I88: 0 | J88: 0 | K88: 1 | L88: 0 | M88: 0 | N88: 0 | O88: 0 | P88: 0 | Q88: 0 | R88: =SUM(I88:Q88) -> 1
E89: 82 | F89: sob | G89: 84 | H89: 新岡部変電所 | I89: 0 | J89: 0 | K89: 1 | L89: 0 | M89: 0 | N89: 0 | O89: 0 | P89: 0 | Q89: 0 | R89: =SUM(I89:Q89) -> 1
E90: 83 | F90: tmo | G90: 85 | H90: 東毛変電所 | I90: 0 | J90: 0 | K90: 1 | L90: 0 | M90: 0 | N90: 0 | O90: 0 | P90: 0 | Q90: 0 | R90: =SUM(I90:Q90) -> 1
E91: 84 | F91: stt | G91: 86 | H91: 新秩父開閉所 | I91: 0 | J91: 0 | K91: 1 | L91: 0 | M91: 0 | N91: 0 | O91: 0 | P91: 0 | Q91: 0 | R91: =SUM(I91:Q91) -> 1
E92: 85 | F92: kkm | G92: 87 | H92: 北熊谷変電所 | I92: 0 | J92: 0 | K92: 1 | L92: 0 | M92: 0 | N92: 0 | O92: 0 | P92: 0 | Q92: 0 | R92: =SUM(I92:Q92) -> 1
E93: 86 | F93: ssm | G93: 88 | H93: 西毛変電所 | I93: 0 | J93: 0 | K93: 1 | L93: 0 | M93: 0 | N93: 0 | O93: 0 | P93: 0 | Q93: 0 | R93: =SUM(I93:Q93) -> 1
E94: 87 | F94: kfj | G94: 89 | H94: 新富士変電所 | I94: 0 | J94: 0 | K94: 1 | L94: 0 | M94: 0 | N94: 0 | O94: 0 | P94: 0 | Q94: 0 | R94: =SUM(I94:Q94) -> 1
E95: 88 | F95: shn | G95: 90 | H95: 新榛名変電所 | I95: 0 | J95: 0 | K95: 1 | L95: 0 | M95: 0 | N95: 0 | O95: 0 | P95: 0 | Q95: 0 | R95: =SUM(I95:Q95) -> 1
E96: 89 | F96: stk | G96: 91 | H96: 新所沢変電所 | I96: 0 | J96: 0 | K96: 1 | L96: 0 | M96: 0 | N96: 0 | O96: 0 | P96: 0 | Q96: 0 | R96: =SUM(I96:Q96) -> 1
E97: 90 | F97: htn | G97: 92 | H97: 新秦野変電所 | I97: 0 | J97: 0 | K97: 1 | L97: 0 | M97: 0 | N97: 0 | O97: 0 | P97: 0 | Q97: 0 | R97: =SUM(I97:Q97) -> 1
E98: 91 | F98: ksg | G98: 93 | H98: 北相模変電所 | I98: 0 | J98: 0 | K98: 1 | L98: 0 | M98: 0 | N98: 0 | O98: 0 | P98: 0 | Q98: 0 | R98: =SUM(I98:Q98) -> 1
E99: 92 | F99: stm | G99: 94 | H99: 新多摩変電所 | I99: 0 | J99: 0 | K99: 1 | L99: 0 | M99: 0 | N99: 0 | O99: 0 | P99: 0 | Q99: 0 | R99: =SUM(I99:Q99) -> 1
... E223: 216 | F223: okc | G223: 218 | H223: 大河内発電所 | I223: 0 | J223: 0 | K223: 0 | L223: 0 | M223: 0 | N223: 1 | O223: 0 | P223: 0 | Q223: 0 | R223: =SUM(I223:Q223) -> 1
F224: mdk | G224: 219 | H224: 舞鶴火力 | I224: 0 | J224: 0 | K224: 0 | L224: 0 | M224: 0 | N224: 1 | O224: 0 | P224: 0 | Q224: 0 | R224: =SUM(I224:Q224) -> 1
E225: 217 | F225: ayb | G225: 220 | H225: 新綾部変電所 | I225: 0 | J225: 0 | K225: 0 | L225: 0 | M225: 0 | N225: 1 | O225: 0 | P225: 0 | Q225: 0 | R225: =SUM(I225:Q225) -> 1
E226: 218 | F226: ryn | G226: 221 | H226: 嶺南変電所 | I226: 0 | J226: 0 | K226: 0 | L226: 0 | M226: 0 | N226: 1 | O226: 0 | P226: 0 | Q226: 0 | R226: =SUM(I226:Q226) -> 1
E227: 219 | F227: ymt | G227: 222 | H227: 東大和開閉所 | I227: 0 | J227: 0 | K227: 0 | L227: 0 | M227: 0 | N227: 1 | O227: 0 | P227: 0 | Q227: 0 | R227: =SUM(I227:Q227) -> 1
E228: 220 | F228: kkt | G228: 223 | H228: 紀北変換所 | I228: 0 | J228: 0 | K228: 0 | L228: 0 | M228: 0 | N228: 1 | O228: 0 | P228: 0 | Q228: 0 | R228: =SUM(I228:Q228) -> 1
E229: 221 | F229: kya | G229: 224 | H229: １３４Ｔ（北大和線） | I229: 0 | J229: 0 | K229: 0 | L229: 0 | M229: 0 | N229: 1 | O229: 0 | P229: 0 | Q229: 0 | R229: =SUM(I229:Q229) -> 1
E230: 222 | F230: sgi | G230: 225 | H230: 信貴変電所 | I230: 0 | J230: 0 | K230: 0 | L230: 0 | M230: 0 | N230: 1 | O230: 0 | P230: 0 | Q230: 0 | R230: =SUM(I230:Q230) -> 1
E231: 223 | F231: hmj | G231: 226 | H231: 姫路変電所 | I231: 0 | J231: 0 | K231: 0 | L231: 0 | M231: 0 | N231: 1 | O231: 0 | P231: 0 | Q231: 0 | R231: =SUM(I231:Q231) -> 1
E232: 224 | F232: kbe | G232: 227 | H232: 神戸変電所 | I232: 0 | J232: 0 | K232: 0 | L232: 0 | M232: 0 | N232: 1 | O232: 0 | P232: 0 | Q232: 0 | R232: =SUM(I232:Q232) -> 1
E233: 225 | F233: ksi | G233: 228 | H233: ４２Ｔ（北神線） | I233: 0 | J233: 0 | K233: 0 | L233: 0 | M233: 0 | N233: 1 | O233: 0 | P233: 0 | Q233: 0 | R233: =SUM(I233:Q233) -> 1
E234: 226 | F234: nkb | G234: 229 | H234: 西神戸変電所 | I234: 0 | J234: 0 | K234: 0 | L234: 0 | M234: 0 | N234: 1 | O234: 0 | P234: 0 | Q234: 0 | R234: =SUM(I234:Q234) -> 1
E235: 227 | F235: kkg | G235: 230 | H235: 新加古川変電所 | I235: 0 | J235: 0 | K235: 0 | L235: 0 | M235: 0 | N235: 1 | O235: 0 | P235: 0 | Q235: 0 | R235: =SUM(I235:Q235) -> 1
E236: 228 | F236: itn | G236: 231 | H236: 伊丹変電所 | I236: 0 | J236: 0 | K236: 0 | L236: 0 | M236: 0 | N236: 1 | O236: 0 | P236: 0 | Q236: 0 | R236: =SUM(I236:Q236) -> 1
... E266: 258 | F266: hir | G266: 261 | H266: 広見変電所 | I266: 0 | J266: 0 | K266: 0 | L266: 0 | M266: 0 | N266: 0 | O266: 1 | P266: 0 | Q266: 0 | R266: =SUM(I266:Q266) -> 1
F267: ika | G267: 262 | H267: 伊方原子力 | I267: 0 | J267: 0 | K267: 0 | L267: 0 | M267: 0 | N267: 0 | O267: 1 | P267: 0 | Q267: 0 | R267: =SUM(I267:Q267) -> 1
E268: 259 | F268: osu | G268: 263 | H268: 大洲変電所 | I268: 0 | J268: 0 | K268: 0 | L268: 0 | M268: 0 | N268: 0 | O268: 1 | P268: 0 | Q268: 0 | R268: =SUM(I268:Q268) -> 1
E269: 260 | F269: mty | G269: 264 | H269: 松山変電所 | I269: 0 | J269: 0 | K269: 0 | L269: 0 | M269: 0 | N269: 0 | O269: 1 | P269: 0 | Q269: 0 | R269: =SUM(I269:Q269) -> 1
E270: 261 | F270: kmt | G270: 265 | H270: 北松山変電所 | I270: 0 | J270: 0 | K270: 0 | L270: 0 | M270: 0 | N270: 0 | O270: 1 | P270: 0 | Q270: 0 | R270: =SUM(I270:Q270) -> 1
...

Sheet TRN
A1: Number of Branches | L1: MAX δ
A2: =ROWS(TI) -> 461 | H2: Node2->Node1 | I2: Node1->Node2 | L2: =PI()/12 -> 0.26179939 | U2: O&M rate | V2: 耐用年数 | Z2: yen | AA2: kW | AB2: km | AG2: GW | AH2: 10^8yen/ 2GW/km
A3: BRN # | B3: Code1 | C3: Code2 | D3: Node1 | E3: Node2 | F3: Distance[km] | G3: X [1000MVAベース] | H3: Maximum Flow1 | I3: Maximum Flow2 | J3: Construction Cost [kYen/kW] | K3: Loss | L3: Minimum Capacity [GW] | M3: Maximum Capacity [GW] | N3: BRN NAME | O3: Node1 | P3: Node2 | U3: 0.01 | V3: 25 | W3: =440*10^6*131 -> 57640000000 | Z3: =W3 -> 57640000000 | AA3: =700*10^3 -> 700000 | AB3: 244 | AC3: =Z3/AA3/AB3 -> 337.47073 | AD3: =Z3/AA3 -> 82342.857 | AE3: =Z3/AA3/AB3 -> 337.47073 | AG3: =AA3/10^6 -> 0.7 | AH3: =(Z3-314*10^8)*(2/AG3)/AB3/10^8 -> 3.0725995
A4: 0 | B4: hkd | C4: uwk | D4: =VLOOKUP(B4,SYS!$F$5:$G$360,2,FALSE) -> 32 | E4: =VLOOKUP(C4,SYS!$F$5:$G$360,2,FALSE) -> 33 | F4: 45 | G4: 0 | H4: -1 | I4: -1 | J4: 0 | K4: =F4*0.0002 -> 0.009 | L4: 0.6 | M4: 0.6 | N4: 北本連系線 | O4: =VLOOKUP(TRN!D4,SYS!$G$5:$H$360,2,FALSE) -> 電発函館変換所 | P4: =VLOOKUP(TRN!E4,SYS!$G$5:$H$360,2,FALSE) -> 上北変電所 | R4: Unit Construction Cost for Upper [Yen/kW/km] | T4: 北海道->東北 | W4: =48*1000*500*131 -> 3144000000 | Z4: =600*10^6*131 -> 78600000000 | AA4: =1000*10^3 -> 1000000 | AB4: 260 | AC4: =Z4/AA4/AB4 -> 302.30769 | AD4: =Z4/AA4 -> 78600 | AE4: =Z4/AA4/AB4 -> 302.30769 | AG4: =AA4/10^6 -> 1 | AH4: =(Z4-314*10^8)*(2/AG4)/AB4/10^8 -> 3.6307692
A5: 1 | B5: sma | C5: miw | D5: =VLOOKUP(B5,SYS!$F$5:$G$360,2,FALSE) -> 37 | E5: =VLOOKUP(C5,SYS!$F$5:$G$360,2,FALSE) -> 63 | F5: 21.903165 | G5: =$L$2/L5 -> 0.00721 | H5: =6.31-L19 -> 4.054 | I5: =10.28-M19 -> 8.024 | J5: 0 | K5: =F5*0.0002 -> 0.004380633 | L5: 36.310595 | M5: 36.310595 | N5: 相馬双葉幹線 | O5: =VLOOKUP(TRN!D5,SYS!$G$5:$H$360,2,FALSE) -> 南相馬変電所 | P5: =VLOOKUP(TRN!E5,SYS!$G$5:$H$360,2,FALSE) -> 南いわき開閉所 | R5: 0 | T5: 東北->東京 | V5: v1 | W5: =430*10^8/300000/122 -> 1174.8634 | Z5: =1350*10^6*131 -> 176850000000 | AA5: =1400*10^3 -> 1400000 | AB5: 600 | AC5: =Z5/AA5/AB5 -> 210.53571 | AD5: =Z5/AA5 -> 126321.43 | AE5: =Z5/AA5/AB5 -> 210.53571 | AG5: =AA5/10^6 -> 1.4 | AH5: =(Z5-314*10^8)*(2/AG5)/AB5/10^8 -> 3.4630952
A6: 2 | B6: fkm | C6: mfm | D6: =VLOOKUP(B6,SYS!$F$5:$G$360,2,FALSE) -> 139 | E6: =VLOOKUP(C6,SYS!$F$5:$G$360,2,FALSE) -> 202 | F6: 0 | G6: 0 | H6: -1 | I6: -1 | J6: 0 | K6: =F6*0.0002 -> 0 | L6: 0.3 | M6: 0.3 | N6: 南福光連系所 | O6: =VLOOKUP(TRN!D6,SYS!$G$5:$H$360,2,FALSE) -> 南福光連係所 | P6: =VLOOKUP(TRN!E6,SYS!$G$5:$H$360,2,FALSE) -> 南福光変電所 | R6: 500 | T6: 中部->北陸 | V6: 0.044 | W6: 1200 yen/kW/km | Z6: =1400*10^6*131 -> 183400000000 | AA6: =1400*10^3 -> 1400000 | AB6: 600 | AC6: =Z6/AA6/AB6 -> 218.33333 | AD6: =Z6/AA6 -> 131000 | AE6: =Z6/AA6/AB6 -> 218.33333 | AG6: =AA6/10^6 -> 1.4 | AH6: =(Z6-314*10^8)*(2/AG6)/AB6/10^8 -> 3.6190476
A7: 3 | B7: ech | C7: ryn | D7: =VLOOKUP(B7,SYS!$F$5:$G$360,2,FALSE) -> 199 | E7: =VLOOKUP(C7,SYS!$F$5:$G$360,2,FALSE) -> 221 | F7: 104.83015 | G7: =$L$2/L7 -> 0.0395 | H7: 1.5 | I7: 1.9 | J7: 0 | K7: =F7*0.0002 -> 0.02096603 | L7: 6.6278326 | M7: 6.6278326 | N7: 越前嶺南線 | O7: =VLOOKUP(TRN!D7,SYS!$G$5:$H$360,2,FALSE) -> 越前変電所 | P7: =VLOOKUP(TRN!E7,SYS!$G$5:$H$360,2,FALSE) -> 嶺南変電所 | R7: 500 | T7: 北陸->関西 | W7: =1200*700*10^3*140 -> 117600000000 | Z7: =700*10^6*131 -> 91700000000 | AA7: =2000*10^3 -> 2000000 | AB7: 64 | AC7: =Z7/AA7/AB7 -> 716.40625 | AD7: =Z7/AA7 -> 45850 | AE7: =Z7/AA7/AB7 -> 716.40625 | AG7: =AA7/10^6 -> 2 | AH7: =(Z7-314*10^8)*(2/AG7)/AB7/10^8 -> 9.421875
A8: 4 | B8: mie | C8: hom | D8: =VLOOKUP(B8,SYS!$F$5:$G$360,2,FALSE) -> 133 | E8: =VLOOKUP(C8,SYS!$F$5:$G$360,2,FALSE) -> 215 | F8: 17.914013 | G8: =$L$2/L8 -> 0.00675 | H8: 2.5 | I8: 1.24 | J8: 0 | K8: =F8*0.0002 -> 0.0035828025 | L8: 38.785094 | M8: 38.785094 | N8: 三重東近江線 | O8: =VLOOKUP(TRN!D8,SYS!$G$5:$H$360,2,FALSE) -> 三重開閉所 | P8: =VLOOKUP(TRN!E8,SYS!$G$5:$H$360,2,FALSE) -> 東近江開閉所 | R8: 500 | T8: 中部->関西 | V8: v2 | W8: =J27*300000 -> 14716626
A9: 5 | B9: kkt | C9: ana | D9: =VLOOKUP(B9,SYS!$F$5:$G$360,2,FALSE) -> 223 | E9: =VLOOKUP(C9,SYS!$F$5:$G$360,2,FALSE) -> 260 | F9: 0 | G9: 0 | H9: -1 | I9: -1 | J9: 0 | K9: =F9*0.0002 -> 0 | L9: 1.4 | M9: 1.4 | N9: 阿南紀北直流幹線 | O9: =VLOOKUP(TRN!D9,SYS!$G$5:$H$360,2,FALSE) -> 紀北変換所 | P9: =VLOOKUP(TRN!E9,SYS!$G$5:$H$360,2,FALSE) -> 阿南変換所 | R9: 500 | T9: 関西->四国 | V9: =1/0.03 -> 33.333333 | W9: =J21*300000 -> 29437443
A10: 6 | B10: san | C10: hok | D10: =VLOOKUP(B10,SYS!$F$5:$G$360,2,FALSE) -> 258 | E10: =VLOOKUP(C10,SYS!$F$5:$G$360,2,FALSE) -> 286 | F10: 105.49363 | G10: =$L$2/L10 -> 0.03975 | H10: 1.2 | I10: 1.2 | J10: 0 | K10: =F10*0.0002 -> 0.021098726 | L10: 6.5861481 | M10: 6.5861481 | N10: 本四連系線 | O10: =VLOOKUP(TRN!D10,SYS!$G$5:$H$360,2,FALSE) -> 讃岐変電所 | P10: =VLOOKUP(TRN!E10,SYS!$G$5:$H$360,2,FALSE) -> 東岡山（変） | R10: 500 | T10: 四国->中国 | W10: =8*10^8/(J20*1000) -> 7367.5917
A11: 7 | B11: yzk | C11: cht | D11: =VLOOKUP(B11,SYS!$F$5:$G$360,2,FALSE) -> 217 | E11: =VLOOKUP(C11,SYS!$F$5:$G$360,2,FALSE) -> 281 | F11: 70.329087 | G11: =$L$2/L11 -> 0.0265 | H11: 2.1 | I11: 1.39 | J11: 0 | K11: =F11*0.0002 -> 0.014065817 | L11: 9.8792222 | M11: 9.8792222 | N11: 山崎智頭線 | O11: =VLOOKUP(TRN!D11,SYS!$G$5:$H$360,2,FALSE) -> 山崎開閉所 | P11: =VLOOKUP(TRN!E11,SYS!$G$5:$H$360,2,FALSE) -> 智頭（変） | R11: 500 | T11: 関西->中国 | V11: v3 | Y11: 567 | Z11: =(135.27*Y11+47805)*2*10^6/10^8 -> 2490.0618
A12: 8 | B12: nba | C12: hok | D12: =VLOOKUP(B12,SYS!$F$5:$G$360,2,FALSE) -> 209 | E12: =VLOOKUP(C12,SYS!$F$5:$G$360,2,FALSE) -> 286 | F12: 75.636943 | G12: =$L$2/L12 -> 0.0285 | H12: 2.1 | I12: 1.39 | J12: 0 | K12: =F12*0.0002 -> 0.015127389 | L12: 9.1859434 | M12: 9.1859434 | N12: 西播岡山線 | O12: =VLOOKUP(TRN!D12,SYS!$G$5:$H$360,2,FALSE) -> 西播変電所 | P12: =VLOOKUP(TRN!E12,SYS!$G$5:$H$360,2,FALSE) -> 東岡山（変） | T12: 関西->中国 | V12: 1.03 | Y12: 425 | Z12: =(135.27*Y12+47805)*2*10^6/10^8 -> 2105.895
A13: 9 | B13: sym | C13: kky | D13: =VLOOKUP(B13,SYS!$F$5:$G$360,2,FALSE) -> 278 | E13: =VLOOKUP(C13,SYS!$F$5:$G$360,2,FALSE) -> 308 | F13: 55.86518 | G13: =$L$2/L13 -> 0.02105 | H13: 2.78 | I13: 0.32 | J13: 0 | K13: =F13*0.0002 -> 0.011173036 | L13: 12.437026 | M13: 12.437026 | N13: 関門連系線 | O13: =VLOOKUP(TRN!D13,SYS!$G$5:$H$360,2,FALSE) -> 新山口（変） | P13: =VLOOKUP(TRN!E13,SYS!$G$5:$H$360,2,FALSE) -> 北九州変電所 | T13: 中国->九州 | V13: 均等化年経費率 | Y13: 480 | Z13: =(135.27*Y13+47805)*2*10^6/10^8 -> 2254.692
A14: 10 | B14: kfj | C14: hse | D14: =VLOOKUP(B14,SYS!$F$5:$G$360,2,FALSE) -> 89 | E14: =VLOOKUP(C14,SYS!$F$5:$G$360,2,FALSE) -> 141 | F14: 100 | G14: 0 | H14: -1 | I14: -1 | J14: 0 | K14: =F14*0.0002 -> 0.02 | L14: 0.6 | M14: 0.6 | N14: 佐久間FC | O14: =VLOOKUP(TRN!D14,SYS!$G$5:$H$360,2,FALSE) -> 新富士変電所 | P14: =VLOOKUP(TRN!E14,SYS!$G$5:$H$360,2,FALSE) -> 東栄変電所 | R14: =0.6*0.6/3 -> 0.12 | T14: 東京->中部 | V14: =1/BLT*(1-V6*(V9-BLT/(V12^BLT-1)))+V6+O_M_rate -> 0.075560878 | Y14: 720 | Z14: =(135.27*Y14+47805)*2*10^6/10^8 -> 2903.988
A15: 11 | B15: kfj | C15: his | D15: =VLOOKUP(B15,SYS!$F$5:$G$360,2,FALSE) -> 89 | E15: =VLOOKUP(C15,SYS!$F$5:$G$360,2,FALSE) -> 195 | F15: 100 | G15: 0 | H15: -1 | I15: -1 | J15: 0 | K15: =F15*0.0002 -> 0.02 | L15: 0.9 | M15: 0.9 | N15: 東清水FC | O15: =VLOOKUP(TRN!D15,SYS!$G$5:$H$360,2,FALSE) -> 新富士変電所 | P15: =VLOOKUP(TRN!E15,SYS!$G$5:$H$360,2,FALSE) -> 東清水変電所 | R15: =0.6*0.9/3 -> 0.18 | T15: 東京->中部 | Y15: 296 | Z15: =(135.27*Y15+47805)*2*10^6/10^8 -> 1756.8984
A16: 12 | B16: hkt | C16: ibt | D16: =VLOOKUP(B16,SYS!$F$5:$G$360,2,FALSE) -> 17 | E16: =VLOOKUP(C16,SYS!$F$5:$G$360,2,FALSE) -> 60 | F16: 122 | G16: 0 | H16: -1 | I16: -1 | J16: 0 | K16: =F16*0.0002 -> 0.0244 | L16: 0.3 | M16: 0.3 | N16: 北本連系線2 | O16: =VLOOKUP(TRN!D16,SYS!$G$5:$H$360,2,FALSE) -> 北斗変換所 | P16: =VLOOKUP(TRN!E16,SYS!$G$5:$H$360,2,FALSE) -> 今別変換所 | T16: 北海道->東北 | Y16: 429 | Z16: =(135.27*Y16+47805)*2*10^6/10^8 -> 2116.7166
A17: 13 | B17: ssi | C17: nks | D17: =VLOOKUP(B17,SYS!$F$5:$G$360,2,FALSE) -> 132 | E17: =VLOOKUP(C17,SYS!$F$5:$G$360,2,FALSE) -> 166 | F17: 5 | G17: 0 | H17: -1 | I17: -1 | J17: 0 | K17: =F17*0.0002 -> 0.001 | L17: 0.6 | M17: 0.6 | N17: 新信濃1FC | O17: =VLOOKUP(TRN!D17,SYS!$G$5:$H$360,2,FALSE) -> 新信濃変電所 | P17: =VLOOKUP(TRN!E17,SYS!$G$5:$H$360,2,FALSE) -> 中信変電所 | T17: 東京->中部 | Y17: 424 | Z17: =(135.27*Y17+47805)*2*10^6/10^8 -> 2103.1896
A18: 14 | B18: ssi | C18: hid | D18: =VLOOKUP(B18,SYS!$F$5:$G$360,2,FALSE) -> 132 | E18: =VLOOKUP(C18,SYS!$F$5:$G$360,2,FALSE) -> 198 | F18: 89 | G18: 0 | H18: -1 | I18: -1 | J18: 0 | K18: =F18*0.0002 -> 0.0178 | L18: 0.9 | M18: 0.9 | N18: 新信濃2FC | O18: =VLOOKUP(TRN!D18,SYS!$G$5:$H$360,2,FALSE) -> 新信濃変電所 | P18: =VLOOKUP(TRN!E18,SYS!$G$5:$H$360,2,FALSE) -> 飛騨変換所 | R18: =0.6*1.5/3 -> 0.3 | T18: 東京->中部 | Y18: 466 | Z18: =(135.27*Y18+47805)*2*10^6/10^8 -> 2216.8164
A19: 15 | B19: sma | C19: sfu | D19: =VLOOKUP(B19,SYS!$F$5:$G$360,2,FALSE) -> 37 | E19: =VLOOKUP(C19,SYS!$F$5:$G$360,2,FALSE) -> 62 | F19: 20 | G19: =$L$2/L19 -> 0.11604583 | H19: -1 | I19: -1 | J19: 0 | K19: =F19*0.0002 -> 0.004 | L19: 2.256 | M19: 2.256 | N19: いわき幹線 | O19: =VLOOKUP(TRN!D19,SYS!$G$5:$H$360,2,FALSE) -> 南相馬変電所 | P19: =VLOOKUP(TRN!E19,SYS!$G$5:$H$360,2,FALSE) -> 新福島変電所 | T19: 東北→東京
A20: 16 | B20: not | C20: kzk | D20: =VLOOKUP(B20,SYS!$F$5:$G$360,2,FALSE) -> 11 | E20: =VLOOKUP(C20,SYS!$F$5:$G$360,2,FALSE) -> 82 | F20: 750 | G20: 0 | H20: -1 | I20: -1 | J20: =(T20+30000)/1000*0.7 -> 108.58365 | K20: 0.01 | L20: 0 | M20: 10 | N20: 北海道→東北 | O20: =VLOOKUP(TRN!D20,SYS!$G$5:$H$360,2,FALSE) -> 西小樽変電所 | P20: =VLOOKUP(TRN!E20,SYS!$G$5:$H$360,2,FALSE) -> 柏崎刈羽原子力 | T20: =F20*124.51+31737 -> 125119.5 | U20: 北海道→東京 | Y20: 172 | Z20: =(135.27*Y20+47805)*2*10^6/10^8 -> 1421.4288
A21: 17 | B21: tmk | C21: fkn | D21: =VLOOKUP(B21,SYS!$F$5:$G$360,2,FALSE) -> 12 | E21: =VLOOKUP(C21,SYS!$F$5:$G$360,2,FALSE) -> 61 | F21: 630 | G21: 0 | H21: -1 | I21: -1 | J21: =(T21+30000)/1000*0.7 -> 98.12481 | K21: 0.01 | L21: 0 | M21: 10 | N21: 北海道→東京 | O21: =VLOOKUP(TRN!D21,SYS!$G$5:$H$360,2,FALSE) -> 苫小牧変電所 | P21: =VLOOKUP(TRN!E21,SYS!$G$5:$H$360,2,FALSE) -> 旧福島第二原子力 | T21: =F21*124.51+31737 -> 110178.3 | U21: 北海道→東京 | Y21: 1120 | Z21: =(135.27*Y21+47805)*2*10^6/10^8 -> 3986.148
A22: 18 | B22: akt | C22: kzk | D22: =VLOOKUP(B22,SYS!$F$5:$G$360,2,FALSE) -> 40 | E22: =VLOOKUP(C22,SYS!$F$5:$G$360,2,FALSE) -> 82 | F22: 300 | G22: 0 | H22: -1 | I22: -1 | J22: =(T22+30000)/1000*0.7 -> 69.363 | K22: 0.01 | L22: 0 | M22: 10 | N22: 東北→東京 | O22: =VLOOKUP(TRN!D22,SYS!$G$5:$H$360,2,FALSE) -> 秋田変電所 | P22: =VLOOKUP(TRN!E22,SYS!$G$5:$H$360,2,FALSE) -> 柏崎刈羽原子力 | T22: =F22*124.51+31737 -> 69090 | U22: 東北→東京 | V22: 39.81344155846961, 140.08600868575846 | W22: 37.421658772924616, 138.5955646412592
B23: kzk | C23: sks | D23: =VLOOKUP(B23,SYS!$F$5:$G$360,2,FALSE) -> 82 | E23: =VLOOKUP(C23,SYS!$F$5:$G$360,2,FALSE) -> 168 | F23: 45 | G23: 0 | H23: -1 | I23: -1 | J23: =(T23+30000)/1000*0.7 -> 47.137965 | K23: 0.01 | L23: 0 | M23: 10 | N23: 東京→中部（柏崎） | O23: =VLOOKUP(TRN!D23,SYS!$G$5:$H$360,2,FALSE) -> 柏崎刈羽原子力 | P23: =VLOOKUP(TRN!E23,SYS!$G$5:$H$360,2,FALSE) -> 新北信変電所 | T23: =F23*124.51+31737 -> 37339.95 | U23: 東京→中部
A24: 19 | B24: sks | C24: mdk | D24: =VLOOKUP(B24,SYS!$F$5:$G$360,2,FALSE) -> 168 | E24: =VLOOKUP(C24,SYS!$F$5:$G$360,2,FALSE) -> 219 | F24: 420 | G24: 0 | H24: -1 | I24: -1 | J24: =(T24+30000)/1000*0.7 -> 79.82184 | K24: 0.01 | L24: 0 | M24: 0 | N24: 東京→関西（日本海） | O24: =VLOOKUP(TRN!D24,SYS!$G$5:$H$360,2,FALSE) -> 新北信変電所 | P24: =VLOOKUP(TRN!E24,SYS!$G$5:$H$360,2,FALSE) -> 舞鶴火力 | T24: =F24*124.51+31737 -> 84031.2 | U24: 東京→関西（日本海） | V24: 37.421658772924616, 138.5955646412592 | W24: 35.5029669878051, 135.39713661369862
A25: 20 | B25: htn | C25: mta | D25: =VLOOKUP(B25,SYS!$F$5:$G$360,2,FALSE) -> 92 | E25: =VLOOKUP(C25,SYS!$F$5:$G$360,2,FALSE) -> 151 | F25: 380 | G25: 0 | H25: -1 | I25: -1 | J25: =(T25+30000)/1000*0.7 -> 76.33556 | K25: 0.01 | L25: 0 | M25: 10 | N25: 東京→関西（太平洋） | O25: =VLOOKUP(TRN!D25,SYS!$G$5:$H$360,2,FALSE) -> 新秦野変電所 | P25: =VLOOKUP(TRN!E25,SYS!$G$5:$H$360,2,FALSE) -> 尾鷲三田変電所 | T25: =F25*124.51+31737 -> 79050.8 | U25: 東京→関西（太平洋） | V25: 35.40066582144089, 139.2250703092658 | W25: 34.071374924761415, 136.17701106893637
A26: 21 | B26: kkt | C26: ana | D26: =VLOOKUP(B26,SYS!$F$5:$G$360,2,FALSE) -> 223 | E26: =VLOOKUP(C26,SYS!$F$5:$G$360,2,FALSE) -> 260 | F26: 85 | G26: 0 | H26: -1 | I26: -1 | J26: =(T26+30000)/1000*0.7 -> 50.624245 | K26: 0.01 | L26: 0 | M26: 10 | N26: 関西→四国 | O26: =VLOOKUP(TRN!D26,SYS!$G$5:$H$360,2,FALSE) -> 紀北変換所 | P26: =VLOOKUP(TRN!E26,SYS!$G$5:$H$360,2,FALSE) -> 阿南変換所 | T26: =F26*124.51+31737 -> 42320.35 | U26: 関西→四国
A27: 22 | B27: ika | C27: hky | D27: =VLOOKUP(B27,SYS!$F$5:$G$360,2,FALSE) -> 262 | E27: =VLOOKUP(C27,SYS!$F$5:$G$360,2,FALSE) -> 311 | F27: 67 | G27: 0 | H27: -1 | I27: -1 | J27: =(T27+30000)/1000*0.7 -> 49.055419 | K27: 0.01 | L27: 0 | M27: 10 | N27: 四国→九州 | O27: =VLOOKUP(TRN!D27,SYS!$G$5:$H$360,2,FALSE) -> 伊方原子力 | P27: =VLOOKUP(TRN!E27,SYS!$G$5:$H$360,2,FALSE) -> 東九州変電所 | T27: =F27*124.51+31737 -> 40079.17 | U27: 四国→九州
A28: 23 | B28: ryn | C28: fko | D28: =VLOOKUP(B28,SYS!$F$5:$G$360,2,FALSE) -> 221 | E28: =VLOOKUP(C28,SYS!$F$5:$G$360,2,FALSE) -> 327 | F28: 600 | G28: 0 | H28: -1 | I28: -1 | J28: =(T28+30000)/1000*0.7 -> 95.5101 | K28: 0.01 | L28: 0 | M28: 10 | N28: 関西→九州 | O28: =VLOOKUP(TRN!D28,SYS!$G$5:$H$360,2,FALSE) -> 嶺南変電所 | P28: =VLOOKUP(TRN!E28,SYS!$G$5:$H$360,2,FALSE) -> 東福岡変電所 | T28: =F28*124.51+31737 -> 106443 | U28: 関西→九州
A29: 24 | B29: nab | C29: nno | D29: =VLOOKUP(B29,SYS!$F$5:$G$360,2,FALSE) -> 0 | E29: =VLOOKUP(C29,SYS!$F$5:$G$360,2,FALSE) -> 1 | F29: 33 | G29: 0.13011 | H29: -1 | I29: -1 | J29: 0 | K29: =F29*0.0002 -> 0.0066 | L29: 1.809 | M29: 1.809 | N29: 道央北幹線 | O29: =VLOOKUP(TRN!D29,SYS!$G$5:$H$360,2,FALSE) -> 西当別変電所 | P29: =VLOOKUP(TRN!E29,SYS!$G$5:$H$360,2,FALSE) -> 西野変電所 | T29: 1.5564227 | U29: 0.89935636
A30: 25 | B30: eni | C30: neh | D30: =VLOOKUP(B30,SYS!$F$5:$G$360,2,FALSE) -> 14 | E30: =VLOOKUP(C30,SYS!$F$5:$G$360,2,FALSE) -> 4 | F30: 41 | G30: 0.15932 | H30: -1 | I30: -1 | J30: 0 | K30: =F30*0.0002 -> 0.0082 | L30: 1.356 | M30: 1.356 | N30: 道央西幹線 | O30: =VLOOKUP(TRN!D30,SYS!$G$5:$H$360,2,FALSE) -> 恵庭変電所 | P30: =VLOOKUP(TRN!E30,SYS!$G$5:$H$360,2,FALSE) -> 苗穂変電所 | T30: 1.4691763 | U30: 1.5479588
A31: 26 | B31: msb | C31: nfb | D31: =VLOOKUP(B31,SYS!$F$5:$G$360,2,FALSE) -> 3 | E31: =VLOOKUP(C31,SYS!$F$5:$G$360,2,FALSE) -> 2 | F31: 74 | G31: 0.29012 | H31: -1 | I31: -1 | J31: 0 | K31: =F31*0.0002 -> 0.0148 | L31: 1.197 | M31: 1.197 | N31: 道央南幹線 | O31: =VLOOKUP(TRN!D31,SYS!$G$5:$H$360,2,FALSE) -> 南早来変電所 | P31: =VLOOKUP(TRN!E31,SYS!$G$5:$H$360,2,FALSE) -> 西双葉開閉所 | T31: 2.1672625 | U31: 1.4951921
A32: 27 | B32: msb | C32: nab | D32: =VLOOKUP(B32,SYS!$F$5:$G$360,2,FALSE) -> 3 | E32: =VLOOKUP(C32,SYS!$F$5:$G$360,2,FALSE) -> 0 | F32: 92 | G32: 0.35852 | H32: -1 | I32: -1 | J32: 0 | K32: =F32*0.0002 -> 0.0184 | L32: 1.892 | M32: 1.892 | N32: 道央東幹線 | O32: =VLOOKUP(TRN!D32,SYS!$G$5:$H$360,2,FALSE) -> 南早来変電所 | P32: =VLOOKUP(TRN!E32,SYS!$G$5:$H$360,2,FALSE) -> 西当別変電所 | T32: 1.2601353 | U32: 0.94172972
A33: 28 | B33: nab | C33: neh | D33: =VLOOKUP(B33,SYS!$F$5:$G$360,2,FALSE) -> 0 | E33: =VLOOKUP(C33,SYS!$F$5:$G$360,2,FALSE) -> 4 | F33: 19 | G33: =$L$2/L33 -> 0.20485085 | H33: -1 | I33: -1 | J33: 0 | K33: =F33*0.0002 -> 0.0038 | L33: 1.278 | M33: 1.278 | N33: 苗穂北線 | O33: =VLOOKUP(TRN!D33,SYS!$G$5:$H$360,2,FALSE) -> 西当別変電所 | P33: =VLOOKUP(TRN!E33,SYS!$G$5:$H$360,2,FALSE) -> 苗穂変電所 | Q33: 0.639 | T33: 1.3559539 | U33: 2.0384274
A34: 29 | B34: nab | C34: sno | D34: =VLOOKUP(B34,SYS!$F$5:$G$360,2,FALSE) -> 0 | E34: =VLOOKUP(C34,SYS!$F$5:$G$360,2,FALSE) -> 5 | F34: 17 | G34: 0.18806 | H34: -1 | I34: -1 | J34: 0 | K34: =F34*0.0002 -> 0.0034 | L34: 0.639 | M34: 0.639 | N34: 篠路線 | O34: =VLOOKUP(TRN!D34,SYS!$G$5:$H$360,2,FALSE) -> 西当別変電所 | P34: =VLOOKUP(TRN!E34,SYS!$G$5:$H$360,2,FALSE) -> 篠路変電所 | T34: 3.1502744 | U34: 3.3226684
A35: 30 | B35: nsp | C35: sno | D35: =VLOOKUP(B35,SYS!$F$5:$G$360,2,FALSE) -> 6 | E35: =VLOOKUP(C35,SYS!$F$5:$G$360,2,FALSE) -> 5 | F35: 9 | G35: 0.09992 | H35: -1 | I35: -1 | J35: 0 | K35: =F35*0.0002 -> 0.0018 | L35: 0.276 | M35: 0.276 | N35: 西札幌線 | O35: =VLOOKUP(TRN!D35,SYS!$G$5:$H$360,2,FALSE) -> 西札幌変電所 | P35: =VLOOKUP(TRN!E35,SYS!$G$5:$H$360,2,FALSE) -> 篠路変電所 | T35: 4.7656234 | U35: 364.15263
A36: 31 | B36: nno | C36: nsp | D36: =VLOOKUP(B36,SYS!$F$5:$G$360,2,FALSE) -> 1 | E36: =VLOOKUP(C36,SYS!$F$5:$G$360,2,FALSE) -> 6 | F36: 10 | G36: 0.11697 | H36: -1 | I36: -1 | J36: 0 | K36: =F36*0.0002 -> 0.002 | L36: 0.558 | M36: 0.558 | N36: 室蘭西幹線1 | O36: =VLOOKUP(TRN!D36,SYS!$G$5:$H$360,2,FALSE) -> 西野変電所 | P36: =VLOOKUP(TRN!E36,SYS!$G$5:$H$360,2,FALSE) -> 西札幌変電所 | T36: 2.1355192 | U36: 6678.9815
A37: 32 | B37: ftb | C37: neh | D37: =VLOOKUP(B37,SYS!$F$5:$G$360,2,FALSE) -> 7 | E37: =VLOOKUP(C37,SYS!$F$5:$G$360,2,FALSE) -> 4 | F37: 42 | G37: 0.48493 | H37: -1 | I37: -1 | J37: 0 | K37: =F37*0.0002 -> 0.0084 | L37: 0.555 | M37: 0.555 | N37: 室蘭西幹線2 | O37: =VLOOKUP(TRN!D37,SYS!$G$5:$H$360,2,FALSE) -> 双葉開閉所 | P37: =VLOOKUP(TRN!E37,SYS!$G$5:$H$360,2,FALSE) -> 苗穂変電所 | T37: 3323.2712 | U37: 5.2022465
A38: 33 | B38: nmr | C38: ftb | D38: =VLOOKUP(B38,SYS!$F$5:$G$360,2,FALSE) -> 8 | E38: =VLOOKUP(C38,SYS!$F$5:$G$360,2,FALSE) -> 7 | F38: 45 | G38: 0.52346 | H38: -1 | I38: -1 | J38: 0 | K38: =F38*0.0002 -> 0.009 | L38: 0.478 | M38: 0.478 | N38: 室蘭西幹線3 | O38: =VLOOKUP(TRN!D38,SYS!$G$5:$H$360,2,FALSE) -> 西室蘭開閉所 | P38: =VLOOKUP(TRN!E38,SYS!$G$5:$H$360,2,FALSE) -> 双葉開閉所 | T38: 5.0252826 | U38: 3.923306
A39: 34 | B39: nmr | C39: mrn | D39: =VLOOKUP(B39,SYS!$F$5:$G$360,2,FALSE) -> 8 | E39: =VLOOKUP(C39,SYS!$F$5:$G$360,2,FALSE) -> 9 | F39: 7 | G39: 0.08037 | H39: -1 | I39: -1 | J39: 0 | K39: =F39*0.0002 -> 0.0014 | L39: 0.368 | M39: 0.368 | N39: 室蘭西幹線4 | O39: =VLOOKUP(TRN!D39,SYS!$G$5:$H$360,2,FALSE) -> 西室蘭開閉所 | P39: =VLOOKUP(TRN!E39,SYS!$G$5:$H$360,2,FALSE) -> 室蘭変電所 | T39: 5.3510481 | U39: 6.1656098
A40: 35 | B40: nno | C40: mkj | D40: =VLOOKUP(B40,SYS!$F$5:$G$360,2,FALSE) -> 1 | E40: =VLOOKUP(C40,SYS!$F$5:$G$360,2,FALSE) -> 10 | F40: 16 | G40: =$L$2/L40 -> 0.61311332 | H40: -1 | I40: -1 | J40: 0 | K40: =F40*0.0002 -> 0.0032 | L40: 0.427 | M40: 0.427 | N40: 南九条線 | O40: =VLOOKUP(TRN!D40,SYS!$G$5:$H$360,2,FALSE) -> 西野変電所 | P40: =VLOOKUP(TRN!E40,SYS!$G$5:$H$360,2,FALSE) -> 南九条変電所 | T40: 2.9491075 | U40: 12.835238
A41: 36 | B41: nno | C41: not | D41: =VLOOKUP(B41,SYS!$F$5:$G$360,2,FALSE) -> 1 | E41: =VLOOKUP(C41,SYS!$F$5:$G$360,2,FALSE) -> 11 | F41: 35 | G41: =$L$2/L41 -> 0.87558324 | H41: -1 | I41: -1 | J41: 0 | K41: =F41*0.0002 -> 0.007 | L41: 0.299 | M41: 0.299 | N41: 西小樽線 | O41: =VLOOKUP(TRN!D41,SYS!$G$5:$H$360,2,FALSE) -> 西野変電所 | P41: =VLOOKUP(TRN!E41,SYS!$G$5:$H$360,2,FALSE) -> 西小樽変電所 | T41: 4.4293399 | U41: 22.870144
A42: 37 | B42: tmk | C42: ftb | D42: =VLOOKUP(B42,SYS!$F$5:$G$360,2,FALSE) -> 12 | E42: =VLOOKUP(C42,SYS!$F$5:$G$360,2,FALSE) -> 7 | F42: 53 | G42: 0.613 | H42: -1 | I42: -1 | J42: 0 | K42: =F42*0.0002 -> 0.0106 | L42: 0.434 | M42: 0.434 | N42: 双葉幹線 | O42: =VLOOKUP(TRN!D42,SYS!$G$5:$H$360,2,FALSE) -> 苫小牧変電所 | P42: =VLOOKUP(TRN!E42,SYS!$G$5:$H$360,2,FALSE) -> 双葉開閉所 | Q42: 0.217 | T42: 7.3339688 | U42: 4.7428383
A43: 38 | B43: mrn | C43: tmk | D43: =VLOOKUP(B43,SYS!$F$5:$G$360,2,FALSE) -> 9 | E43: =VLOOKUP(C43,SYS!$F$5:$G$360,2,FALSE) -> 12 | F43: 61 | G43: 0.72754 | H43: -1 | I43: -1 | J43: 0 | K43: =F43*0.0002 -> 0.0122 | L43: 0.288 | M43: 0.288 | N43: 室蘭東幹線 | O43: =VLOOKUP(TRN!D43,SYS!$G$5:$H$360,2,FALSE) -> 室蘭変電所 | P43: =VLOOKUP(TRN!E43,SYS!$G$5:$H$360,2,FALSE) -> 苫小牧変電所 | T43: 7.4963032 | U43: 7.8629176
A44: 39 | B44: msb | C44: tib | D44: =VLOOKUP(B44,SYS!$F$5:$G$360,2,FALSE) -> 3 | E44: =VLOOKUP(C44,SYS!$F$5:$G$360,2,FALSE) -> 13 | F44: 24 | G44: 0.27414 | H44: -1 | I44: -1 | J44: 0 | K44: =F44*0.0002 -> 0.0048 | L44: 0.611 | M44: 0.611 | N44: 追分線 | O44: =VLOOKUP(TRN!D44,SYS!$G$5:$H$360,2,FALSE) -> 南早来変電所 | P44: =VLOOKUP(TRN!E44,SYS!$G$5:$H$360,2,FALSE) -> 追分開閉所 | T44: 21.223006 | U44: 3.2385757
A45: 40 | B45: tib | C45: eni | D45: =VLOOKUP(B45,SYS!$F$5:$G$360,2,FALSE) -> 13 | E45: =VLOOKUP(C45,SYS!$F$5:$G$360,2,FALSE) -> 14 | F45: 17 | G45: =$L$2/L45 -> 0.00043926072 | H45: -1 | I45: -1 | J45: 0 | K45: =F45*0.0002 -> 0.0034 | L45: 596 | M45: 596 | N45: 追分恵庭線 | O45: =VLOOKUP(TRN!D45,SYS!$G$5:$H$360,2,FALSE) -> 追分開閉所 | P45: =VLOOKUP(TRN!E45,SYS!$G$5:$H$360,2,FALSE) -> 恵庭変電所 | T45: -0.011479636 | U45: -0.011474396
A46: 41 | B46: eni | C46: msp | D46: =VLOOKUP(B46,SYS!$F$5:$G$360,2,FALSE) -> 14 | E46: =VLOOKUP(C46,SYS!$F$5:$G$360,2,FALSE) -> 15 | F46: 18 | G46: =$L$2/L46 -> 0.00048934465 | H46: -1 | I46: -1 | J46: 0 | K46: =F46*0.0002 -> 0.0036 | L46: 535 | M46: 535 | N46: 恵庭南札線 | O46: =VLOOKUP(TRN!D46,SYS!$G$5:$H$360,2,FALSE) -> 恵庭変電所 | P46: =VLOOKUP(TRN!E46,SYS!$G$5:$H$360,2,FALSE) -> 南札幌変電所 | T46: -0.011081676 | U46: -0.011079658
A47: 42 | B47: keb | C47: msp | D47: =VLOOKUP(B47,SYS!$F$5:$G$360,2,FALSE) -> 16 | E47: =VLOOKUP(C47,SYS!$F$5:$G$360,2,FALSE) -> 15 | F47: 15 | G47: 0.17804 | H47: -1 | I47: -1 | J47: 0 | K47: =F47*0.0002 -> 0.003 | L47: 0.736 | M47: 0.736 | N47: 南札幌幹線 | O47: =VLOOKUP(TRN!D47,SYS!$G$5:$H$360,2,FALSE) -> 北江別変電所 | P47: =VLOOKUP(TRN!E47,SYS!$G$5:$H$360,2,FALSE) -> 南札幌変電所 | Q47: 0.368 | T47: 2.6933332 | U47: 2.9637953
A48: 43 | B48: nab | C48: keb | D48: =VLOOKUP(B48,SYS!$F$5:$G$360,2,FALSE) -> 0 | E48: =VLOOKUP(C48,SYS!$F$5:$G$360,2,FALSE) -> 16 | F48: 21 | G48: 0.22362 | H48: -1 | I48: -1 | J48: 0 | K48: =F48*0.0002 -> 0.0042 | L48: 0.825 | M48: 0.825 | N48: 北江別線 | O48: =VLOOKUP(TRN!D48,SYS!$G$5:$H$360,2,FALSE) -> 西当別変電所 | P48: =VLOOKUP(TRN!E48,SYS!$G$5:$H$360,2,FALSE) -> 北江別変電所 | T48: 2.0611126 | U48: 3.219898
A49: 44 | B49: nfb | C49: hkt | D49: =VLOOKUP(B49,SYS!$F$5:$G$360,2,FALSE) -> 2 | E49: =VLOOKUP(C49,SYS!$F$5:$G$360,2,FALSE) -> 17 | F49: 176 | G49: 0.6949 | H49: -1 | I49: -1 | J49: 0 | K49: =F49*0.0002 -> 0.0352 | L49: 0.733 | M49: 0.733 | N49: 道南幹線 | O49: =VLOOKUP(TRN!D49,SYS!$G$5:$H$360,2,FALSE) -> 西双葉開閉所 | P49: =VLOOKUP(TRN!E49,SYS!$G$5:$H$360,2,FALSE) -> 北斗変換所 | T49: 4.3597168 | U49: 2.5326739
A50: 45 | B50: oon | C50: nne | D50: =VLOOKUP(B50,SYS!$F$5:$G$360,2,FALSE) -> 18 | E50: =VLOOKUP(C50,SYS!$F$5:$G$360,2,FALSE) -> 19 | F50: 10 | G50: 0.10976 | H50: -1 | I50: -1 | J50: 0 | K50: =F50*0.0002 -> 0.002 | L50: 0.611 | M50: 0.611 | N50: 大野線 | O50: =VLOOKUP(TRN!D50,SYS!$G$5:$H$360,2,FALSE) -> 大野変電所 | P50: =VLOOKUP(TRN!E50,SYS!$G$5:$H$360,2,FALSE) -> 北七飯変電所 | T50: 4.0669152 | U50: 3.0813347
A51: 46 | B51: ftb | C51: nne | D51: =VLOOKUP(B51,SYS!$F$5:$G$360,2,FALSE) -> 7 | E51: =VLOOKUP(C51,SYS!$F$5:$G$360,2,FALSE) -> 19 | F51: 164 | G51: 1.09848 | H51: -1 | I51: -1 | J51: 0 | K51: =F51*0.0002 -> 0.0328 | L51: 0.197 | M51: 0.197 | N51: 函館幹線 | O51: =VLOOKUP(TRN!D51,SYS!$G$5:$H$360,2,FALSE) -> 双葉開閉所 | P51: =VLOOKUP(TRN!E51,SYS!$G$5:$H$360,2,FALSE) -> 北七飯変電所 | T51: 8422.6936 | U51: 36206.438
A52: 47 | B52: nab | C52: ary | D52: =VLOOKUP(B52,SYS!$F$5:$G$360,2,FALSE) -> 0 | E52: =VLOOKUP(C52,SYS!$F$5:$G$360,2,FALSE) -> 20 | F52: 123 | G52: 1.07571 | H52: -1 | I52: -1 | J52: 0 | K52: =F52*0.0002 -> 0.0246 | L52: 0.383 | M52: 0.383 | N52: 道北幹線 | O52: =VLOOKUP(TRN!D52,SYS!$G$5:$H$360,2,FALSE) -> 西当別変電所 | P52: =VLOOKUP(TRN!E52,SYS!$G$5:$H$360,2,FALSE) -> 旭川嵐山開閉所 | T52: 5.5867751 | U52: 13.082445
A53: 48 | B53: ary | C53: akw | D53: =VLOOKUP(B53,SYS!$F$5:$G$360,2,FALSE) -> 20 | E53: =VLOOKUP(C53,SYS!$F$5:$G$360,2,FALSE) -> 21 | F53: 22 | G53: =$L$2/L53 -> 1.2064488 | H53: -1 | I53: -1 | J53: 0 | K53: =F53*0.0002 -> 0.0044 | L53: 0.217 | M53: 0.217 | N53: 旭川南線 | O53: =VLOOKUP(TRN!D53,SYS!$G$5:$H$360,2,FALSE) -> 旭川嵐山開閉所 | P53: =VLOOKUP(TRN!E53,SYS!$G$5:$H$360,2,FALSE) -> 旭川変電所 | T53: 6.8899508 | U53: 15.61424
A54: 49 | B54: ary | C54: nny | D54: =VLOOKUP(B54,SYS!$F$5:$G$360,2,FALSE) -> 20 | E54: =VLOOKUP(C54,SYS!$F$5:$G$360,2,FALSE) -> 22 | F54: 66 | G54: 0.04613 | H54: -1 | I54: -1 | J54: 0 | K54: =F54*0.0002 -> 0.0132 | L54: 0.169 | M54: 0.169 | N54: 名寄幹線1 | O54: =VLOOKUP(TRN!D54,SYS!$G$5:$H$360,2,FALSE) -> 旭川嵐山開閉所 | P54: =VLOOKUP(TRN!E54,SYS!$G$5:$H$360,2,FALSE) -> 西名寄変電所 | T54: 13.684152 | U54: 13.10939
A55: 50 | B55: nas | C55: ary | D55: =VLOOKUP(B55,SYS!$F$5:$G$360,2,FALSE) -> 23 | E55: =VLOOKUP(C55,SYS!$F$5:$G$360,2,FALSE) -> 20 | F55: 4 | G55: =$L$2/L55 -> 0.7745544 | H55: -1 | I55: -1 | J55: 0 | K55: =F55*0.0002 -> 0.0008 | L55: 0.338 | M55: 0.338 | N55: 名寄幹線2 | O55: =VLOOKUP(TRN!D55,SYS!$G$5:$H$360,2,FALSE) -> 西旭川変電所 | P55: =VLOOKUP(TRN!E55,SYS!$G$5:$H$360,2,FALSE) -> 旭川嵐山開閉所 | Q55: 0.169 | T55: 5.9930745 | U55: 10.724597
A56: 51 | B56: ntw | C56: nas | D56: =VLOOKUP(B56,SYS!$F$5:$G$360,2,FALSE) -> 24 | E56: =VLOOKUP(C56,SYS!$F$5:$G$360,2,FALSE) -> 23 | F56: 57 | G56: 0.69651 | H56: -1 | I56: -1 | J56: 0 | K56: =F56*0.0002 -> 0.0114 | L56: 0.213 | M56: 0.213 | N56: 旭川幹線 | O56: =VLOOKUP(TRN!D56,SYS!$G$5:$H$360,2,FALSE) -> 西滝川変電所 | P56: =VLOOKUP(TRN!E56,SYS!$G$5:$H$360,2,FALSE) -> 西旭川変電所 | T56: 7.7364343 | U56: 634.4226
A57: 52 | B57: msb | C57: kar | D57: =VLOOKUP(B57,SYS!$F$5:$G$360,2,FALSE) -> 3 | E57: =VLOOKUP(C57,SYS!$F$5:$G$360,2,FALSE) -> 25 | F57: 114 | G57: 0.45945 | H57: -1 | I57: -1 | J57: 0 | K57: =F57*0.0002 -> 0.0228 | L57: 0.949 | M57: 0.949 | N57: 狩勝幹線 | O57: =VLOOKUP(TRN!D57,SYS!$G$5:$H$360,2,FALSE) -> 南早来変電所 | P57: =VLOOKUP(TRN!E57,SYS!$G$5:$H$360,2,FALSE) -> 北新得変電所 | T57: 2.5270177 | U57: 1.9571578
A58: 53 | B58: tib | C58: kar | D58: =VLOOKUP(B58,SYS!$F$5:$G$360,2,FALSE) -> 13 | E58: =VLOOKUP(C58,SYS!$F$5:$G$360,2,FALSE) -> 25 | F58: 99 | G58: =$L$2/L58 -> 0.0013289309 | H58: -1 | I58: -1 | J58: 0 | K58: =F58*0.0002 -> 0.0198 | L58: 197 | M58: 197 | N58: 新得追分線 | O58: =VLOOKUP(TRN!D58,SYS!$G$5:$H$360,2,FALSE) -> 追分開閉所 | P58: =VLOOKUP(TRN!E58,SYS!$G$5:$H$360,2,FALSE) -> 北新得変電所 | T58: -0.0043584274 | U58: -0.0043734721
A59: 54 | B59: isz | C59: msb | D59: =VLOOKUP(B59,SYS!$F$5:$G$360,2,FALSE) -> 26 | E59: =VLOOKUP(C59,SYS!$F$5:$G$360,2,FALSE) -> 3 | F59: 75 | G59: 0.88145 | H59: -1 | I59: -1 | J59: 0 | K59: =F59*0.0002 -> 0.015 | L59: 0.306 | M59: 0.306 | N59: 日高幹線 | O59: =VLOOKUP(TRN!D59,SYS!$G$5:$H$360,2,FALSE) -> 岩清水開閉所 | P59: =VLOOKUP(TRN!E59,SYS!$G$5:$H$360,2,FALSE) -> 南早来変電所 | T59: 4.7367514 | U59: 29.710079
A60: 55 | B60: kar | C60: kmm | D60: =VLOOKUP(B60,SYS!$F$5:$G$360,2,FALSE) -> 25 | E60: =VLOOKUP(C60,SYS!$F$5:$G$360,2,FALSE) -> 27 | F60: 30 | G60: =$L$2/L60 -> 1.3289309 | H60: -1 | I60: -1 | J60: 0 | K60: =F60*0.0002 -> 0.006 | L60: 0.197 | M60: 0.197 | N60: 岩松西線 | O60: =VLOOKUP(TRN!D60,SYS!$G$5:$H$360,2,FALSE) -> 北新得変電所 | P60: =VLOOKUP(TRN!E60,SYS!$G$5:$H$360,2,FALSE) -> 北芽室変電所 | T60: 28.545622 | U60: 9.5740219
A61: 56 | B61: kar | C61: nos | D61: =VLOOKUP(B61,SYS!$F$5:$G$360,2,FALSE) -> 25 | E61: =VLOOKUP(C61,SYS!$F$5:$G$360,2,FALSE) -> 28 | F61: 33 | G61: =$L$2/L61 -> 0.95897212 | H61: -1 | I61: -1 | J61: 0 | K61: =F61*0.0002 -> 0.0066 | L61: 0.273 | M61: 0.273 | N61: 西音更線 | O61: =VLOOKUP(TRN!D61,SYS!$G$5:$H$360,2,FALSE) -> 北新得変電所 | P61: =VLOOKUP(TRN!E61,SYS!$G$5:$H$360,2,FALSE) -> 西音更変電所 | T61: 3534.3783 | U61: 4.475905
A62: 57 | B62: kar | C62: umb | D62: =VLOOKUP(B62,SYS!$F$5:$G$360,2,FALSE) -> 25 | E62: =VLOOKUP(C62,SYS!$F$5:$G$360,2,FALSE) -> 29 | F62: 110 | G62: 0.99254 | H62: -1 | I62: -1 | J62: 0 | K62: =F62*0.0002 -> 0.022 | L62: 0.578 | M62: 0.578 | N62: 道東幹線 | O62: =VLOOKUP(TRN!D62,SYS!$G$5:$H$360,2,FALSE) -> 北新得変電所 | P62: =VLOOKUP(TRN!E62,SYS!$G$5:$H$360,2,FALSE) -> 宇円別変電所 | Q62: 0.289 | T62: 32.459333 | U62: 2.593421
A63: 58 | B63: umb | C63: hkr | D63: =VLOOKUP(B63,SYS!$F$5:$G$360,2,FALSE) -> 29 | E63: =VLOOKUP(C63,SYS!$F$5:$G$360,2,FALSE) -> 30 | F63: 29 | G63: =$L$2/L63 -> 0.47427425 | H63: -1 | I63: -1 | J63: 0 | K63: =F63*0.0002 -> 0.0058 | L63: 0.552 | M63: 0.552 | N63: 釧路北線 | O63: =VLOOKUP(TRN!D63,SYS!$G$5:$H$360,2,FALSE) -> 宇円別変電所 | P63: =VLOOKUP(TRN!E63,SYS!$G$5:$H$360,2,FALSE) -> 東釧路変電所 | Q63: 0.276 | T63: 25.300168 | U63: 2.9073827
A64: 59 | B64: hkr | C64: nhb | D64: =VLOOKUP(B64,SYS!$F$5:$G$360,2,FALSE) -> 30 | E64: =VLOOKUP(C64,SYS!$F$5:$G$360,2,FALSE) -> 31 | F64: 59 | G64: =$L$2/L64 -> 1.0471976 | H64: -1 | I64: -1 | J64: 0 | K64: =F64*0.0002 -> 0.0118 | L64: 0.25 | M64: 0.25 | N64: 西春別線 | O64: =VLOOKUP(TRN!D64,SYS!$G$5:$H$360,2,FALSE) -> 東釧路変電所 | P64: =VLOOKUP(TRN!E64,SYS!$G$5:$H$360,2,FALSE) -> 西春別変電所 | Q64: 0.125 | T64: 656.55403 | U64: 6.2022914
A65: 60 | B65: hkd | C65: nne | D65: =VLOOKUP(B65,SYS!$F$5:$G$360,2,FALSE) -> 32 | E65: =VLOOKUP(C65,SYS!$F$5:$G$360,2,FALSE) -> 19 | F65: 1 | G65: =$L$2/L65 -> 0.36666581 | H65: -1 | I65: -1 | J65: 0 | K65: =F65*0.0002 -> 0.0002 | L65: 0.714 | M65: 0.714 | N65: 北本七飯線 | O65: =VLOOKUP(TRN!D65,SYS!$G$5:$H$360,2,FALSE) -> 電発函館変換所 | P65: =VLOOKUP(TRN!E65,SYS!$G$5:$H$360,2,FALSE) -> 北七飯変電所 | T65: 1.8954631 | U65: 359.32229
A66: 61 | B66: hkt | C66: oon | D66: =VLOOKUP(B66,SYS!$F$5:$G$360,2,FALSE) -> 17 | E66: =VLOOKUP(C66,SYS!$F$5:$G$360,2,FALSE) -> 18 | F66: 1 | G66: 0.01493 | H66: -1 | I66: -1 | J66: 0 | K66: =F66*0.0002 -> 0.0002 | L66: 1.064 | M66: 1.064 | N66: 北斗幹線 | O66: =VLOOKUP(TRN!D66,SYS!$G$5:$H$360,2,FALSE) -> 北斗変換所 | P66: =VLOOKUP(TRN!E66,SYS!$G$5:$H$360,2,FALSE) -> 大野変電所 | T66: 1.8995417 | U66: 1.9848371
A67: 62 | B67: uwk | C67: iwt | D67: =VLOOKUP(B67,SYS!$F$5:$G$360,2,FALSE) -> 33 | E67: =VLOOKUP(C67,SYS!$F$5:$G$360,2,FALSE) -> 34 | F67: 114 | G67: 0.1292 | H67: -1 | I67: -1 | J67: 0 | K67: =F67*0.0002 -> 0.0228 | L67: 9.872 | M67: 9.872 | N67: 十和田幹線 | O67: =VLOOKUP(TRN!D67,SYS!$G$5:$H$360,2,FALSE) -> 上北変電所 | P67: =VLOOKUP(TRN!E67,SYS!$G$5:$H$360,2,FALSE) -> 岩手変電所 | T67: 0.16745894 | U67: 0.23480496 | V67: 9.872 | W67: 9.872
A68: 63 | B68: iwt | C68: myg | D68: =VLOOKUP(B68,SYS!$F$5:$G$360,2,FALSE) -> 34 | E68: =VLOOKUP(C68,SYS!$F$5:$G$360,2,FALSE) -> 35 | F68: 184 | G68: 0.2085 | H68: -1 | I68: -1 | J68: 0 | K68: =F68*0.0002 -> 0.0368 | L68: 9.872 | M68: 9.872 | N68: 北上幹線 | O68: =VLOOKUP(TRN!D68,SYS!$G$5:$H$360,2,FALSE) -> 岩手変電所 | P68: =VLOOKUP(TRN!E68,SYS!$G$5:$H$360,2,FALSE) -> 宮城変電所 | T68: 0.16363972 | U68: 0.24599517 | V68: 9.872 | W68: 9.872
A69: 64 | B69: myg | C69: nsd | D69: =VLOOKUP(B69,SYS!$F$5:$G$360,2,FALSE) -> 35 | E69: =VLOOKUP(C69,SYS!$F$5:$G$360,2,FALSE) -> 36 | F69: 57 | G69: 0.0443 | H69: -1 | I69: -1 | J69: 0 | K69: =F69*0.0002 -> 0.0114 | L69: 8.888 | M69: 8.888 | N69: 青葉幹線 | O69: =VLOOKUP(TRN!D69,SYS!$G$5:$H$360,2,FALSE) -> 宮城変電所 | P69: =VLOOKUP(TRN!E69,SYS!$G$5:$H$360,2,FALSE) -> 西仙台変電所 | T69: 0.14197231 | U69: 0.48643395 | V69: 8.888 | W69: 8.888
A70: 65 | B70: nsd | C70: sma | D70: =VLOOKUP(B70,SYS!$F$5:$G$360,2,FALSE) -> 36 | E70: =VLOOKUP(C70,SYS!$F$5:$G$360,2,FALSE) -> 37 | F70: 100 | G70: 0.1129 | H70: -1 | I70: -1 | J70: 0 | K70: =F70*0.0002 -> 0.02 | L70: 8.888 | M70: 8.888 | N70: 常磐幹線 | O70: =VLOOKUP(TRN!D70,SYS!$G$5:$H$360,2,FALSE) -> 西仙台変電所 | P70: =VLOOKUP(TRN!E70,SYS!$G$5:$H$360,2,FALSE) -> 南相馬変電所 | T70: 0.14962751 | U70: 0.43971137 | V70: 8.888 | W70: 8.888
A71: 66 | B71: uwk | C71: aom | D71: =VLOOKUP(B71,SYS!$F$5:$G$360,2,FALSE) -> 33 | E71: =VLOOKUP(C71,SYS!$F$5:$G$360,2,FALSE) -> 38 | F71: 46 | G71: 0.1945 | H71: -1 | I71: -1 | J71: 0 | K71: =F71*0.0002 -> 0.0092 | L71: 1.344 | M71: 1.344 | N71: 北青幹線 | O71: =VLOOKUP(TRN!D71,SYS!$G$5:$H$360,2,FALSE) -> 上北変電所 | P71: =VLOOKUP(TRN!E71,SYS!$G$5:$H$360,2,FALSE) -> 青森変電所 | T71: 1.3115314 | U71: 2.6536629 | V71: 1.344 | W71: 1.344
A72: 67 | B72: nsr | C72: aom | D72: =VLOOKUP(B72,SYS!$F$5:$G$360,2,FALSE) -> 39 | E72: =VLOOKUP(C72,SYS!$F$5:$G$360,2,FALSE) -> 38 | F72: 103 | G72: 0.439 | H72: -1 | I72: -1 | J72: 0 | K72: =F72*0.0002 -> 0.0206 | L72: 1.344 | M72: 1.344 | N72: 北奥幹線 | O72: =VLOOKUP(TRN!D72,SYS!$G$5:$H$360,2,FALSE) -> 能代変電所 | P72: =VLOOKUP(TRN!E72,SYS!$G$5:$H$360,2,FALSE) -> 青森変電所 | T72: 1.4049362 | U72: 2.0016361 | V72: 1.344 | W72: 1.344
A73: 68 | B73: uwk | C73: iwt | D73: =VLOOKUP(B73,SYS!$F$5:$G$360,2,FALSE) -> 33 | E73: =VLOOKUP(C73,SYS!$F$5:$G$360,2,FALSE) -> 34 | F73: 103 | G73: 0.1634 | H73: -1 | I73: -1 | J73: 0 | K73: =F73*0.0002 -> 0.0206 | L73: 1.808 | M73: 1.808 | N73: 北部幹線 | O73: =VLOOKUP(TRN!D73,SYS!$G$5:$H$360,2,FALSE) -> 上北変電所 | P73: =VLOOKUP(TRN!E73,SYS!$G$5:$H$360,2,FALSE) -> 岩手変電所 | T73: 0.68211927 | U73: 5789.8696 | V73: 1.808 | W73: 1.808
A74: 69 | B74: nsr | C74: akt | D74: =VLOOKUP(B74,SYS!$F$5:$G$360,2,FALSE) -> 39 | E74: =VLOOKUP(C74,SYS!$F$5:$G$360,2,FALSE) -> 40 | F74: 45 | G74: 0.1867 | H74: -1 | I74: -1 | J74: 0 | K74: =F74*0.0002 -> 0.009 | L74: 3.472 | M74: 3.472 | N74: 大潟幹線 | O74: =VLOOKUP(TRN!D74,SYS!$G$5:$H$360,2,FALSE) -> 能代変電所 | P74: =VLOOKUP(TRN!E74,SYS!$G$5:$H$360,2,FALSE) -> 秋田変電所 | T74: 0.47549526 | U74: 0.78094446 | V74: 3.472 | W74: 3.472
A75: 70 | B75: akt | C75: szk | D75: =VLOOKUP(B75,SYS!$F$5:$G$360,2,FALSE) -> 40 | E75: =VLOOKUP(C75,SYS!$F$5:$G$360,2,FALSE) -> 41 | F75: 83 | G75: 0.3602 | H75: -1 | I75: -1 | J75: 0 | K75: =F75*0.0002 -> 0.0166 | L75: 0.66 | M75: 0.66 | N75: 秋盛幹線 | O75: =VLOOKUP(TRN!D75,SYS!$G$5:$H$360,2,FALSE) -> 秋田変電所 | P75: =VLOOKUP(TRN!E75,SYS!$G$5:$H$360,2,FALSE) -> 雫石開閉所 | T75: 3.0468578 | U75: 5.8852739 | V75: 0.66 | W75: 0.66
A76: 71 | B76: szk | C76: iwt | D76: =VLOOKUP(B76,SYS!$F$5:$G$360,2,FALSE) -> 41 | E76: =VLOOKUP(C76,SYS!$F$5:$G$360,2,FALSE) -> 34 | F76: 38 | G76: 0.1592 | H76: -1 | I76: -1 | J76: 0 | K76: =F76*0.0002 -> 0.0076 | L76: 0.882 | M76: 0.882 | N76: 岩手幹線 | O76: =VLOOKUP(TRN!D76,SYS!$G$5:$H$360,2,FALSE) -> 雫石開閉所 | P76: =VLOOKUP(TRN!E76,SYS!$G$5:$H$360,2,FALSE) -> 岩手変電所 | T76: 2.1743936 | U76: 2.7435584 | V76: 0.882 | W76: 0.882
A77: 72 | B77: akt | C77: ugo | D77: =VLOOKUP(B77,SYS!$F$5:$G$360,2,FALSE) -> 40 | E77: =VLOOKUP(C77,SYS!$F$5:$G$360,2,FALSE) -> 42 | F77: 85 | G77: 0.3608 | H77: -1 | I77: -1 | J77: 0 | K77: =F77*0.0002 -> 0.017 | L77: 0.882 | M77: 0.882 | N77: 秋田幹線 | O77: =VLOOKUP(TRN!D77,SYS!$G$5:$H$360,2,FALSE) -> 秋田変電所 | P77: =VLOOKUP(TRN!E77,SYS!$G$5:$H$360,2,FALSE) -> 羽後変電所 | T77: 1.274615 | U77: 166219.07 | V77: 0.882 | W77: 0.882
A78: 73 | B78: iwt | C78: mzs | D78: =VLOOKUP(B78,SYS!$F$5:$G$360,2,FALSE) -> 34 | E78: =VLOOKUP(C78,SYS!$F$5:$G$360,2,FALSE) -> 43 | F78: 102 | G78: 0.2829 | H78: -1 | I78: -1 | J78: 0 | K78: =F78*0.0002 -> 0.0204 | L78: 0.904 | M78: 0.904 | N78: 早池峰幹線 | O78: =VLOOKUP(TRN!D78,SYS!$G$5:$H$360,2,FALSE) -> 岩手変電所 | P78: =VLOOKUP(TRN!E78,SYS!$G$5:$H$360,2,FALSE) -> 水沢変電所 | T78: 1.5781795 | U78: 1564213.6 | V78: 0.904 | W78: 0.904
... A85: 80 | B85: nsd | C85: sdi | D85: =VLOOKUP(B85,SYS!$F$5:$G$360,2,FALSE) -> 36 | E85: =VLOOKUP(C85,SYS!$F$5:$G$360,2,FALSE) -> 47 | F85: 30 | G85: 0.1284 | H85: -1 | I85: -1 | J85: 0 | K85: =F85*0.0002 -> 0.006 | L85: 1.1 | M85: 1.1 | N85: 仙台幹線 | O85: =VLOOKUP(TRN!D85,SYS!$G$5:$H$360,2,FALSE) -> 西仙台変電所 | P85: =VLOOKUP(TRN!E85,SYS!$G$5:$H$360,2,FALSE) -> 仙台変電所 | T85: 587640.54 | U85: 1.1111128 | V85: 1.1 | W85: 1.1
A86: 81 | B86: hsd | C86: sdi | D86: =VLOOKUP(B86,SYS!$F$5:$G$360,2,FALSE) -> 48 | E86: =VLOOKUP(C86,SYS!$F$5:$G$360,2,FALSE) -> 47 | F86: 16 | G86: =$L$2/L86 -> 0.14480055 | H86: -1 | I86: -1 | J86: 0 | K86: =F86*0.0002 -> 0.0032 | L86: 1.808 | M86: 1.808 | N86: 新仙台火力Ａ線 | O86: =VLOOKUP(TRN!D86,SYS!$G$5:$H$360,2,FALSE) -> 東仙台変電所 | P86: =VLOOKUP(TRN!E86,SYS!$G$5:$H$360,2,FALSE) -> 仙台変電所 | T86: 0.86617424 | U86: 47.482626 | V86: 1.808 | W86: 1.808
A87: 82 | B87: ecg | C87: nsd | D87: =VLOOKUP(B87,SYS!$F$5:$G$360,2,FALSE) -> 49 | E87: =VLOOKUP(C87,SYS!$F$5:$G$360,2,FALSE) -> 36 | F87: 139 | G87: 0.1752 | H87: -1 | I87: -1 | J87: 0 | K87: =F87*0.0002 -> 0.0278 | L87: 3.618 | M87: 3.618 | N87: 朝日幹線 | O87: =VLOOKUP(TRN!D87,SYS!$G$5:$H$360,2,FALSE) -> 越後開閉所 | P87: =VLOOKUP(TRN!E87,SYS!$G$5:$H$360,2,FALSE) -> 西仙台変電所 | T87: 0.67564355 | U87: 0.49179922 | V87: 3.618 | W87: 3.618
A88: 83 | B88: nsd | C88: yzw | D88: =VLOOKUP(B88,SYS!$F$5:$G$360,2,FALSE) -> 36 | E88: =VLOOKUP(C88,SYS!$F$5:$G$360,2,FALSE) -> 50 | F88: 83 | G88: 0.358 | H88: -1 | I88: -1 | J88: 0 | K88: =F88*0.0002 -> 0.0166 | L88: 0.618 | M88: 0.618 | N88: 蔵王幹線 | O88: =VLOOKUP(TRN!D88,SYS!$G$5:$H$360,2,FALSE) -> 西仙台変電所 | P88: =VLOOKUP(TRN!E88,SYS!$G$5:$H$360,2,FALSE) -> 米沢変電所 | T88: 1.9707349 | U88: 3555472.3 | V88: 0.618 | W88: 0.618
A89: 84 | B89: yzw | C89: fks | D89: =VLOOKUP(B89,SYS!$F$5:$G$360,2,FALSE) -> 50 | E89: =VLOOKUP(C89,SYS!$F$5:$G$360,2,FALSE) -> 51 | F89: 38 | G89: 0.1565 | H89: -1 | I89: -1 | J89: 0 | K89: =F89*0.0002 -> 0.0076 | L89: 1.298 | M89: 1.298 | N89: 吾妻幹線 | O89: =VLOOKUP(TRN!D89,SYS!$G$5:$H$360,2,FALSE) -> 米沢変電所 | P89: =VLOOKUP(TRN!E89,SYS!$G$5:$H$360,2,FALSE) -> 福島変電所 | T89: 1.0356638 | U89: 2572328.3 | V89: 1.298 | W89: 1.298
A90: 85 | B90: kni | C90: ecg | D90: =VLOOKUP(B90,SYS!$F$5:$G$360,2,FALSE) -> 52 | E90: =VLOOKUP(C90,SYS!$F$5:$G$360,2,FALSE) -> 49 | F90: 28 | G90: 0.0933 | H90: -1 | I90: -1 | J90: 0 | K90: =F90*0.0002 -> 0.0056 | L90: 1.809 | M90: 1.809 | N90: 北新幹線 | O90: =VLOOKUP(TRN!D90,SYS!$G$5:$H$360,2,FALSE) -> 北新潟変電所 | P90: =VLOOKUP(TRN!E90,SYS!$G$5:$H$360,2,FALSE) -> 越後開閉所 | T90: 1.0906389 | U90: 1.1726757 | V90: 1.809 | W90: 1.809
A91: 86 | B91: ecg | C91: ngt | D91: =VLOOKUP(B91,SYS!$F$5:$G$360,2,FALSE) -> 49 | E91: =VLOOKUP(C91,SYS!$F$5:$G$360,2,FALSE) -> 53 | F91: 30 | G91: 0.0977 | H91: -1 | I91: -1 | J91: 0 | K91: =F91*0.0002 -> 0.006 | L91: 1.809 | M91: 1.809 | N91: 五頭幹線 | O91: =VLOOKUP(TRN!D91,SYS!$G$5:$H$360,2,FALSE) -> 越後開閉所 | P91: =VLOOKUP(TRN!E91,SYS!$G$5:$H$360,2,FALSE) -> 新潟変電所 | T91: 0.71872166 | U91: 54.108545 | V91: 1.809 | W91: 1.809
A92: 87 | B92: ecg | C92: tye | D92: =VLOOKUP(B92,SYS!$F$5:$G$360,2,FALSE) -> 49 | E92: =VLOOKUP(C92,SYS!$F$5:$G$360,2,FALSE) -> 54 | F92: 68 | G92: 0.2526 | H92: -1 | I92: -1 | J92: 0 | K92: =F92*0.0002 -> 0.0136 | L92: 1.809 | M92: 1.809 | N92: 中越幹線 | O92: =VLOOKUP(TRN!D92,SYS!$G$5:$H$360,2,FALSE) -> 越後開閉所 | P92: =VLOOKUP(TRN!E92,SYS!$G$5:$H$360,2,FALSE) -> 中越変電所 | T92: 0.89647734 | U92: 1.5540937 | V92: 1.809 | W92: 1.809
A93: 88 | B93: ngt | C93: yzw | D93: =VLOOKUP(B93,SYS!$F$5:$G$360,2,FALSE) -> 53 | E93: =VLOOKUP(C93,SYS!$F$5:$G$360,2,FALSE) -> 50 | F93: 92 | G93: 0.3934 | H93: -1 | I93: -1 | J93: 0 | K93: =F93*0.0002 -> 0.0184 | L93: 1.32 | M93: 1.32 | N93: 飯豊幹線 | O93: =VLOOKUP(TRN!D93,SYS!$G$5:$H$360,2,FALSE) -> 新潟変電所 | P93: =VLOOKUP(TRN!E93,SYS!$G$5:$H$360,2,FALSE) -> 米沢変電所 | T93: 1.6979102 | U93: 1.5788957 | V93: 1.32 | W93: 1.32
A94: 89 | B94: ngt | C94: hnn | D94: =VLOOKUP(B94,SYS!$F$5:$G$360,2,FALSE) -> 53 | E94: =VLOOKUP(C94,SYS!$F$5:$G$360,2,FALSE) -> 55 | F94: 50 | G94: 0.2226 | H94: -1 | I94: -1 | J94: 0 | K94: =F94*0.0002 -> 0.01 | L94: 0.451 | M94: 0.451 | N94: 新潟幹線 | O94: =VLOOKUP(TRN!D94,SYS!$G$5:$H$360,2,FALSE) -> 新潟変電所 | P94: =VLOOKUP(TRN!E94,SYS!$G$5:$H$360,2,FALSE) -> 本名変電所 | T94: 208755.91 | U94: 159198.8 | V94: 0.451 | W94: 0.451
A95: 90 | B95: hnn | C95: yzw | D95: =VLOOKUP(B95,SYS!$F$5:$G$360,2,FALSE) -> 55 | E95: =VLOOKUP(C95,SYS!$F$5:$G$360,2,FALSE) -> 50 | F95: 78 | G95: 0.3342 | H95: -1 | I95: -1 | J95: 0 | K95: =F95*0.0002 -> 0.0156 | L95: 1.1 | M95: 1.1 | N95: 東北幹線 | O95: =VLOOKUP(TRN!D95,SYS!$G$5:$H$360,2,FALSE) -> 本名変電所 | P95: =VLOOKUP(TRN!E95,SYS!$G$5:$H$360,2,FALSE) -> 米沢変電所 | T95: 75093.09 | U95: 2382.2464 | V95: 1.1 | W95: 1.1
A96: 91 | B96: sma | C96: fks | D96: =VLOOKUP(B96,SYS!$F$5:$G$360,2,FALSE) -> 37 | E96: =VLOOKUP(C96,SYS!$F$5:$G$360,2,FALSE) -> 51 | F96: 55 | G96: =$L$2/L96 -> 0.13607037 | H96: -1 | I96: -1 | J96: 0 | K96: =F96*0.0002 -> 0.011 | L96: 1.924 | M96: 1.924 | N96: 相福幹線 | O96: =VLOOKUP(TRN!D96,SYS!$G$5:$H$360,2,FALSE) -> 南相馬変電所 | P96: =VLOOKUP(TRN!E96,SYS!$G$5:$H$360,2,FALSE) -> 福島変電所 | T96: 176458.54 | U96: 0.8060519 | V96: 1.924 | W96: 1.924
A97: 92 | B97: fks | C97: skg | D97: =VLOOKUP(B97,SYS!$F$5:$G$360,2,FALSE) -> 51 | E97: =VLOOKUP(C97,SYS!$F$5:$G$360,2,FALSE) -> 56 | F97: 46 | G97: 0.1879 | H97: -1 | I97: -1 | J97: 0 | K97: =F97*0.0002 -> 0.0092 | L97: 1.924 | M97: 1.924 | N97: 阿武隈幹線 | O97: =VLOOKUP(TRN!D97,SYS!$G$5:$H$360,2,FALSE) -> 福島変電所 | P97: =VLOOKUP(TRN!E97,SYS!$G$5:$H$360,2,FALSE) -> 須賀川変電所 | Q97: 1.298 | T97: 3712.4152 | U97: 1.16734 | V97: 1.924 | W97: 1.924
A98: 93 | B98: iwk | C98: skg | D98: =VLOOKUP(B98,SYS!$F$5:$G$360,2,FALSE) -> 57 | E98: =VLOOKUP(C98,SYS!$F$5:$G$360,2,FALSE) -> 56 | F98: 12 | G98: 0.2011 | H98: -1 | I98: -1 | J98: 0 | K98: =F98*0.0002 -> 0.0024 | L98: 1.344 | M98: 1.344 | N98: 勿来幹線 | O98: =VLOOKUP(TRN!D98,SYS!$G$5:$H$360,2,FALSE) -> いわき変電所 | P98: =VLOOKUP(TRN!E98,SYS!$G$5:$H$360,2,FALSE) -> 須賀川変電所 | T98: 1.6346817 | U98: 1.5002133 | V98: 1.344 | W98: 1.344
A99: 94 | B99: sng | C99: hje | D99: =VLOOKUP(B99,SYS!$F$5:$G$360,2,FALSE) -> 58 | E99: =VLOOKUP(C99,SYS!$F$5:$G$360,2,FALSE) -> 59 | F99: 39 | G99: =$L$2/L99 -> 0.16955919 | H99: -1 | I99: -1 | J99: 0 | K99: =F99*0.0002 -> 0.0078 | L99: 1.544 | M99: 1.544 | N99: 東上越幹線 | O99: =VLOOKUP(TRN!D99,SYS!$G$5:$H$360,2,FALSE) -> 信濃川変電所 | P99: =VLOOKUP(TRN!E99,SYS!$G$5:$H$360,2,FALSE) -> 東上越変電所 | T99: 1.3277697 | U99: 1.3180226 | V99: 1.544 | W99: 1.544
A100: 95 | B100: sng | C100: hnn | D100: =VLOOKUP(B100,SYS!$F$5:$G$360,2,FALSE) -> 58 | E100: =VLOOKUP(C100,SYS!$F$5:$G$360,2,FALSE) -> 55 | F100: 90 | G100: =$L$2/L100 -> 0.26179939 | H100: -1 | I100: -1 | J100: 0 | K100: =F100*0.0002 -> 0.018 | L100: 1 | M100: 1 | N100: （信濃川本名線） | O100: =VLOOKUP(TRN!D100,SYS!$G$5:$H$360,2,FALSE) -> 信濃川変電所 | P100: =VLOOKUP(TRN!E100,SYS!$G$5:$H$360,2,FALSE) -> 本名変電所 | T100: 2.1836567 | U100: 2.0088676 | V100: 1 | W100: 1
A101: 96 | B101: ibt | C101: aom | D101: =VLOOKUP(B101,SYS!$F$5:$G$360,2,FALSE) -> 60 | E101: =VLOOKUP(C101,SYS!$F$5:$G$360,2,FALSE) -> 38 | F101: 45 | G101: =$L$2/L101 -> 0.2968247 | H101: -1 | I101: -1 | J101: 0 | K101: =F101*0.0002 -> 0.009 | L101: 0.882 | M101: 0.882 | N101: 今別青森線 | O101: =VLOOKUP(TRN!D101,SYS!$G$5:$H$360,2,FALSE) -> 今別変換所 | P101: =VLOOKUP(TRN!E101,SYS!$G$5:$H$360,2,FALSE) -> 青森変電所 | R101: 送電容量とりあえず１ | T101: 2.099362 | U101: 3.7065536 | V101: 0.882 | W101: 0.882
A102: 97 | B102: fkn | C102: sfu | D102: =VLOOKUP(B102,SYS!$F$5:$G$360,2,FALSE) -> 61 | E102: =VLOOKUP(C102,SYS!$F$5:$G$360,2,FALSE) -> 62 | F102: 7.5 | G102: =$L$2/L102 -> 0.055785082 | H102: -1 | I102: -1 | J102: 0 | K102: =F102*0.0002 -> 0.0015 | L102: 4.693 | M102: 4.693 | N102: 富岡線 | O102: =VLOOKUP(TRN!D102,SYS!$G$5:$H$360,2,FALSE) -> 旧福島第二原子力 | P102: =VLOOKUP(TRN!E102,SYS!$G$5:$H$360,2,FALSE) -> 新福島変電所 | T102: 0.42788595 | U102: 0.42308677 | V102: 4.693 | W102: 4.693
A103: 98 | B103: sfu | C103: siw | D103: =VLOOKUP(B103,SYS!$F$5:$G$360,2,FALSE) -> 62 | E103: =VLOOKUP(C103,SYS!$F$5:$G$360,2,FALSE) -> 64 | F103: 45 | G103: =$L$2/L103 -> 0.079550103 | H103: -1 | I103: -1 | J103: 0 | K103: =F103*0.0002 -> 0.009 | L103: 3.291 | M103: 3.291 | N103: 福島幹線（北） | O103: =VLOOKUP(TRN!D103,SYS!$G$5:$H$360,2,FALSE) -> 新福島変電所 | P103: =VLOOKUP(TRN!E103,SYS!$G$5:$H$360,2,FALSE) -> 新いわき開閉所 | T103: 0.51008851 | U103: 0.77128345 | V103: 3.291 | W103: 3.291
A104: 99 | B104: sfu | C104: siw | D104: =VLOOKUP(B104,SYS!$F$5:$G$360,2,FALSE) -> 62 | E104: =VLOOKUP(C104,SYS!$F$5:$G$360,2,FALSE) -> 64 | F104: 45 | G104: =$L$2/L104 -> 0.079550103 | H104: -1 | I104: -1 | J104: 0 | K104: =F104*0.0002 -> 0.009 | L104: 3.291 | M104: 3.291 | N104: 福島幹線（北東） | O104: =VLOOKUP(TRN!D104,SYS!$G$5:$H$360,2,FALSE) -> 新福島変電所 | P104: =VLOOKUP(TRN!E104,SYS!$G$5:$H$360,2,FALSE) -> 新いわき開閉所 | T104: 0.51008851 | U104: 0.77128345 | V104: 3.291 | W104: 3.291
A105: 100 | B105: miw | C105: siw | D105: =VLOOKUP(B105,SYS!$F$5:$G$360,2,FALSE) -> 63 | E105: =VLOOKUP(C105,SYS!$F$5:$G$360,2,FALSE) -> 64 | F105: 30 | G105: =$L$2/L105 -> 0.039775051 | H105: -1 | I105: -1 | J105: 0 | K105: =F105*0.0002 -> 0.006 | L105: 6.582 | M105: 6.582 | N105: 川内線 | O105: =VLOOKUP(TRN!D105,SYS!$G$5:$H$360,2,FALSE) -> 南いわき開閉所 | P105: =VLOOKUP(TRN!E105,SYS!$G$5:$H$360,2,FALSE) -> 新いわき開閉所 | R105: 送電容量とりあえず１ | T105: 0.1811286 | U105: 20893.418 | V105: 6.582 | W105: 6.582
A106: 101 | B106: miw | C106: hgm | D106: =VLOOKUP(B106,SYS!$F$5:$G$360,2,FALSE) -> 63 | E106: =VLOOKUP(C106,SYS!$F$5:$G$360,2,FALSE) -> 65 | F106: 195 | G106: 0.19693 | H106: -1 | I106: -1 | J106: 0 | K106: =F106*0.0002 -> 0.039 | L106: 4.936 | M106: 4.936 | N106: 南いわき幹線 | O106: =VLOOKUP(TRN!D106,SYS!$G$5:$H$360,2,FALSE) -> 南いわき開閉所 | P106: =VLOOKUP(TRN!E106,SYS!$G$5:$H$360,2,FALSE) -> 東群馬変電所 | T106: 0.30395269 | U106: 0.70897887 | V106: 4.936 | W106: 4.936
...
